Workbook
Name BUSCARVV: LAMBDA(IFNA(VLOOKUP('DESCRIPCION BASE'!$A$2,BASE!$A:$J,10,FALSE),""))
Name FUNCIONFECHADEPUBLICACION: LAMBDA(IFNA(XLOOKUP('DESCRIPCION BASE'!$A$2,BASE!$A:$A,BASE!$J:$J),""))

Sheet BASE
A1: id | B1: posicion | C1: Gerencia | D1: ubicacion | E1: Estado | F1: Activa | G1: pdfFileId | H1: UEN | I1: url | J1: fechaPublicacion | K1: Fecha de cierre | L1: Prioridad Empresa | M1: Días de publicación
A2: JOB-2025-000001 | B2: Regional Comercial | C2: Desarrollo Comercial | D2: Corrientes | E2: Activa | F2: TRUE | G2: Corrientes - Regional Comercial (1).pdf | H2: DCAC | I2: =IFERROR(__xludf.DUMMYFUNCTION("G2.url"),"https://drive.google.com/open?id=1l8Q0eQZt8_byy2nd489TZ7B7idptoDL6") -> https://drive.google.com/open?id=1l8Q0eQZt8_byy2nd489TZ7B7idptoDL6 | J2: 46097 | L2: No prioridad Empresa | M2: =IF(OR(K2="",K2>TODAY()),TODAY()-J2,K2-J2) -> 27
A3: JOB-2025-000002 | B3: Regional Comercial | C3: Desarrollo Comercial | D3: La Pampa | E3: Activa | F3: TRUE | G3: La Pampa - Regional Comercial.pdf | H3: DCAC | I3: =IFERROR(__xludf.DUMMYFUNCTION("G3.url"),"https://drive.google.com/open?id=1F9U6Uoe2a3Izrqq7N4KbTau7qNsMkLQi") -> https://drive.google.com/open?id=1F9U6Uoe2a3Izrqq7N4KbTau7qNsMkLQi | J3: 46097 | L3: No prioridad Empresa | M3: =IF(OR(K3="",K3>TODAY()),TODAY()-J3,K3-J3) -> 27
A4: JOB-2025-000003 | B4: Regional Comercial | C4: Desarrollo Comercial | D4: Junin | E4: Activa | F4: TRUE | G4: Junin - Regional Comercial.pdf | H4: DCAC | I4: =IFERROR(__xludf.DUMMYFUNCTION("G4.url"),"https://drive.google.com/open?id=1xbkDWodoJ20DnCYYaEDS90Ja2YlZszkG") -> https://drive.google.com/open?id=1xbkDWodoJ20DnCYYaEDS90Ja2YlZszkG | J4: 46097 | L4: No prioridad Empresa | M4: =IF(OR(K4="",K4>TODAY()),TODAY()-J4,K4-J4) -> 27
A5: JOB-2025-000004 | B5: Regional Comercial | C5: Desarrollo Comercial | D5: Chaco | E5: Activa | F5: TRUE | G5: Chaco - Regional Comercial (1).pdf | H5: DCAC | I5: =IFERROR(__xludf.DUMMYFUNCTION("G5.url"),"https://drive.google.com/open?id=1olNrXEb0uRP_oz0waHdjY3WU_46xgzVK") -> https://drive.google.com/open?id=1olNrXEb0uRP_oz0waHdjY3WU_46xgzVK | J5: 46097 | L5: No prioridad Empresa | M5: =IF(OR(K5="",K5>TODAY()),TODAY()-J5,K5-J5) -> 27
A6: JOB-2025-000005 | B6: Regional Comercial | C6: Desarrollo Comercial | D6: Santa Fe | E6: Activa | F6: TRUE | G6: Santa Fé - Regional Comercial (1).pdf | H6: DCAC | I6: =IFERROR(__xludf.DUMMYFUNCTION("G6.url"),"https://drive.google.com/open?id=1jYkntNdTGfPJiHy93vgOAguoE8XiI40k") -> https://drive.google.com/open?id=1jYkntNdTGfPJiHy93vgOAguoE8XiI40k | J6: 46097 | L6: Prioridad empresa | M6: =IF(OR(K6="",K6>TODAY()),TODAY()-J6,K6-J6) -> 27
A7: JOB-2025-000006 | B7: Analista de Desarrollo Comercial | C7: Desarrollo Comercial | D7: Buenos Aires | E7: Cerrada | F7: FALSE | G7: Analista de Desarrollo Comercial | H7: DCAC | I7: =IFERROR(__xludf.DUMMYFUNCTION("G7.url"),"https://drive.google.com/open?id=1_HsMqdmlRIbUqTR-DK7x0_-oAGe00Amt") -> https://drive.google.com/open?id=1_HsMqdmlRIbUqTR-DK7x0_-oAGe00Amt | J7: 46082 | K7: 46084 | L7: Prioridad empresa | M7: =IF(OR(K7="",K7>TODAY()),TODAY()-J7,K7-J7) -> 2
A8: JOB-2025-000007 | B8: Operador Comercial de Hacienda | C8: Operadores de la mesa | D8: Buenos Aires | E8: Inactiva | F8: FALSE | H8: DCAC | J8: 46097 | M8: =IF(OR(K8="",K8>TODAY()),TODAY()-J8,K8-J8) -> 27
A9: JOB-2025-000008 | B9: Analista de Legales | C9: Administración y Finanzas | D9: Buenos Aires | E9: Activa | F9: TRUE | G9: Búsqueda Analista de Legales (1).pdf | H9: DCAC | I9: =IFERROR(__xludf.DUMMYFUNCTION("G9.url"),"https://drive.google.com/open?id=1OiZybKJo6adgj9UE49khpNGtcOo8uE5I") -> https://drive.google.com/open?id=1OiZybKJo6adgj9UE49khpNGtcOo8uE5I | J9: 46097 | L9: Prioridad empresa | M9: =IF(OR(K9="",K9>TODAY()),TODAY()-J9,K9-J9) -> 27
A10: JOB-2025-000009 | B10: Analista de Finanzas y créditos | C10: Administración y Finanzas | D10: Buenos Aires | E10: Cerrada | F10: FALSE | G10: Búsqueda Analista de Finanzas y Créditos .pdf | H10: DCAC | I10: =IFERROR(__xludf.DUMMYFUNCTION("G10.url"),"https://drive.google.com/open?id=1IqpUOwvapb_zohr0zBNGhV7oku7KjEoO") -> https://drive.google.com/open?id=1IqpUOwvapb_zohr0zBNGhV7oku7KjEoO | J10: 46082 | K10: 46086 | L10: Prioridad empresa | M10: =IF(OR(K10="",K10>TODAY()),TODAY()-J10,K10-J10) -> 4
A11: JOB-2025-000010 | B11: Gerente de Unidad Financiera | C11: Dirección | D11: Buenos Aires | E11: Activa | F11: TRUE | G11: DP. Gerente de Unidad de Negocio (dCP).pdf | H11: DCAC | I11: =IFERROR(__xludf.DUMMYFUNCTION("G11.url"),"https://drive.google.com/open?id=1zPcPLNXgL862TO4hV3tB_ZAl7NEJVsL2") -> https://drive.google.com/open?id=1zPcPLNXgL862TO4hV3tB_ZAl7NEJVsL2 | J11: 46097 | L11: Prioridad empresa | M11: =IF(OR(K11="",K11>TODAY()),TODAY()-J11,K11-J11) -> 27
A12: JOB-2025-000011 | B12: Analista de Operaciones Comerciales | C12: Planificación, soporte y gestión | D12: Buenos Aires | E12: Activa | F12: TRUE | G12: Analista de Operaciones Comerciales.pdf | H12: DCAC | I12: =IFERROR(__xludf.DUMMYFUNCTION("G12.url"),"https://drive.google.com/open?id=1TjUZXJlTvSEmah9HOkhNMoaoH0zq5jvR") -> https://drive.google.com/open?id=1TjUZXJlTvSEmah9HOkhNMoaoH0zq5jvR | J12: 46097 | L12: Prioridad empresa | M12: =IF(OR(K12="",K12>TODAY()),TODAY()-J12,K12-J12) -> 27
A13: JOB-2025-000012 | B13: Analista Contable SR | C13: Administración y Finanzas | D13: Buenos Aires | E13: Cerrada | F13: FALSE | G13: Analista Contable Sr..pdf | H13: DCAC | I13: =IFERROR(__xludf.DUMMYFUNCTION("G13.url"),"https://drive.google.com/open?id=1LQbI7ORA478lNtLZJszL26h2UW5OpFAc") -> https://drive.google.com/open?id=1LQbI7ORA478lNtLZJszL26h2UW5OpFAc | J13: 46002 | K13: 46063 | M13: =IF(OR(K13="",K13>TODAY()),TODAY()-J13,K13-J13) -> 61
A14: JOB-2025-000013 | B14: Analista de At. al Cliente | C14: Planificación, soporte y gestión | D14: Buenos Aires | E14: Cerrada | F14: FALSE | H14: DCAC | J14: 46082 | K14: 46063
A15: JOB-2025-000014 | B15: Analista de Logistica | C15: Planificación, soporte y gestión | D15: Buenos Aires | E15: Cerrada | F15: FALSE | H15: DCAC | J15: 46082 | K15: 46072 | M15: =IF(OR(K15="",K15>TODAY()),TODAY()-J15,K15-J15) -> -10
A16: JOB-2025-000015 | B16: Pasante Machine Learning | C16: Planificación, soporte y gestión | D16: Buenos Aires | E16: Cerrada | F16: FALSE | H16: DCAC | J16: 46082 | K16: 46051 | M16: =IF(OR(K16="",K16>TODAY()),TODAY()-J16,K16-J16) -> -31
A17: JOB-2025-000016 | B17: Regional Comercial | C17: Desarrollo Comercial | D17: Buenos Aires | E17: Activa | F17: TRUE | H17: DCAC | J17: 46097 | L17: No prioridad Empresa | M17: =IF(OR(K17="",K17>TODAY()),TODAY()-J17,K17-J17) -> 27
A18: JOB-2025-000017 | B18: Regional Comercial | C18: Desarrollo Comercial | D18: Santa Fe | E18: Activa | F18: TRUE | H18: DCAC | J18: 46097 | L18: No prioridad Empresa | M18: =IF(OR(K18="",K18>TODAY()),TODAY()-J18,K18-J18) -> 27
A19: JOB-2025-000018 | B19: Regional Comercial | C19: Desarrollo Comercial | D19: Entre Rios | E19: Activa | F19: TRUE | H19: DCAC | J19: 46097 | L19: No prioridad Empresa | M19: =IF(OR(K19="",K19>TODAY()),TODAY()-J20,K19-J20) -> 27
A20: JOB-2025-000019 | B20: Regional Comercial | C20: Desarrollo Comercial | D20: Entre Rios | E20: Activa | F20: TRUE | H20: DCAC | J20: 46097 | L20: No prioridad Empresa | M20: =IF(OR(K20="",K20>TODAY()),TODAY()-J21,K20-J21) -> 27
A21: JOB-2025-000020 | B21: Regional Comercial | C21: Desarrollo Comercial | D21: Cordoba | E21: Activa | F21: TRUE | H21: DCAC | J21: 46097 | L21: No prioridad Empresa | M21: =IF(OR(K21="",K21>TODAY()),TODAY()-#REF!,K21-#REF!) -> #REF!
A22: JOB-2025-000021 | B22: Regional Comercial | C22: Desarrollo Comercial | D22: Salta | E22: Activa | F22: TRUE | H22: DCAC | J22: 46097 | L22: No prioridad Empresa | M22: =IF(OR(K22="",K22>TODAY()),TODAY()-J22,K22-J22) -> 27
A23: JOB-2025-000022 | B23: Regional Comercial | C23: Desarrollo Comercial | D23: Formosa | E23: Activa | F23: TRUE | H23: DCAC | J23: 46097 | L23: No prioridad Empresa | M23: =IF(OR(K23="",K23>TODAY()),TODAY()-J23,K23-J23) -> 27
A24: JOB-2025-000023 | B24: Regional Comercial | C24: Desarrollo Comercial | D24: San Luis | E24: Activa | F24: TRUE | H24: DCAC | J24: 46097 | L24: No prioridad Empresa | M24: =IF(OR(K24="",K24>TODAY()),TODAY()-J24,K24-J24) -> 27
A25: JOB-2025-000024 | B25: Regional Comercial | C25: Desarrollo Comercial | D25: Buenos Aires | E25: Activa | F25: TRUE | H25: DCAC | J25: 46097 | L25: No prioridad Empresa | M25: =IF(OR(K25="",K25>TODAY()),TODAY()-J25,K25-J25) -> 27
A26: JOB-2025-000025 | B26: Regional Comercial | C26: Desarrollo Comercial | D26: Buenos Aires | E26: Activa | F26: TRUE | H26: DCAC | J26: 46097 | L26: No prioridad Empresa | M26: =IF(OR(K26="",K26>TODAY()),TODAY()-J26,K26-J26) -> 27
A27: JOB-2025-000026 | B27: Regional Comercial | C27: Desarrollo Comercial | D27: Buenos Aires | E27: Activa | F27: TRUE | H27: DCAC | J27: 46097 | L27: No prioridad Empresa | M27: =IF(OR(K27="",K27>TODAY()),TODAY()-J27,K27-J27) -> 27
A28: JOB-2025-000027 | B28: Regional Comercial | C28: Desarrollo Comercial | D28: Buenos Aires | E28: Activa | F28: TRUE | H28: DCAC | J28: 46097 | L28: No prioridad Empresa | M28: =IF(OR(K28="",K28>TODAY()),TODAY()-J28,K28-J28) -> 27
A29: JOB-2025-000028 | B29: Regional Comercial | C29: Desarrollo Comercial | D29: Buenos Aires | E29: Activa | F29: TRUE | H29: DCAC | J29: 46097 | L29: No prioridad Empresa | M29: =IF(OR(K29="",K29>TODAY()),TODAY()-J29,K29-J29) -> 27
A30: JOB-2025-000029 | B30: Analista de Mercados | C30: Planificación, soporte y gestión | D30: Buenos Aires | E30: Activa | F30: TRUE | H30: DCAC | J30: 46097 | L30: Prioridad empresa | M30: =IF(OR(K30="",K30>TODAY()),TODAY()-J30,K30-J30) -> 27
A31: JOB-2025-000030 | B31: Analista de Producto Jr. | C31: Desarrollo Tecnológico | D31: Buenos Aires | E31: Activa | F31: TRUE | H31: DCAC | J31: 46097 | L31: Prioridad empresa | M31: =IF(OR(K31="",K31>TODAY()),TODAY()-J31,K31-J31) -> 27
A32: JOB-2025-000031 | B32: Analista de IA | C32: Desarrollo Tecnológico | D32: Buenos Aires | E32: Activa | F32: FALSE | H32: DCAC | J32: 46097 | L32: Prioridad empresa | M32: =IF(OR(K32="",K32>TODAY()),TODAY()-J32,K32-J32) -> 27
A33: JOB-2025-000032 | B33: React Native | C33: Desarrollo Tecnológico | D33: Buenos Aires | E33: Activa | F33: TRUE | H33: DCAC | J33: 46097 | L33: Prioridad empresa | M33: =IF(OR(K33="",K33>TODAY()),TODAY()-J33,K33-J33) -> 27
... A35: JOB-2025-000034 | B35: PHP Developer | C35: Desarrollo Tecnológico | D35: Buenos Aires | E35: Activa | F35: TRUE | H35: DCAC | J35: 46097 | L35: Prioridad empresa | M35: =IF(OR(K35="",K35>TODAY()),TODAY()-J35,K35-J35) -> 27
A36: JOB-2025-000035 | B36: DevOps | C36: Desarrollo Tecnológico | D36: Buenos Aires | E36: Activa | F36: TRUE | H36: DCAC | J36: 46097 | M36: =IF(OR(K36="",K36>TODAY()),TODAY()-J36,K36-J36) -> 27
A37: JOB-2025-000036 | B37: Paid Media | C37: Planificación, soporte y gestión | D37: Buenos Aires | E37: Activa | F37: TRUE | H37: DCAC | J37: 46097 | L37: No prioridad Empresa | M37: =IF(OR(K37="",K37>TODAY()),TODAY()-J37,K37-J37) -> 27
A38: JOB-2025-000037 | B38: Coordinador de Reclutamiento y Selección de Personal | C38: RRHH | D38: Buenos Aires | E38: Activa | F38: TRUE | H38: DCAC | J38: 46097 | L38: Prioridad empresa | M38: =IF(OR(K38="",K38>TODAY()),TODAY()-J38,K38-J38) -> 27
A39: JOB-2025-000038 | B39: Analista de Reclutamiento y Selección de Personal | C39: RRHH | D39: Buenos Aires | E39: Activa | F39: TRUE | H39: DCAC | J39: 46097 | L39: Prioridad empresa | M39: =IF(OR(K39="",K39>TODAY()),TODAY()-J39,K39-J39) -> 27
A40: JOB-2025-000039 | B40: Analista de Atención al Cliente | C40: Planificación, soporte y gestión | D40: Buenos Aires | E40: Activa | F40: TRUE | H40: DCAC | J40: 46097 | L40: No prioridad Empresa | M40: =IF(OR(K40="",K40>TODAY()),TODAY()-J40,K40-J40) -> 27
A41: JOB-2025-000040 | B41: Pasante de Finanzas y Creditos | C41: Administración y Finanzas | D41: Buenos Aires | E41: Activa | F41: TRUE | H41: DCAC | J41: 46097 | L41: Prioridad empresa | M41: =IF(OR(K41="",K41>TODAY()),TODAY()-J41,K41-J41) -> 27
A42: JOB-2025-000041 | F42: FALSE | M42: =IF(OR(K42="",K42>TODAY()),TODAY()-J42,K42-J42) -> 46124
A43: JOB-2025-000042 | F43: FALSE | M43: =IF(OR(K43="",K43>TODAY()),TODAY()-J43,K43-J43) -> 46124
A44: JOB-2025-000043 | F44: FALSE | M44: =IF(OR(K44="",K44>TODAY()),TODAY()-J44,K44-J44) -> 46124
A45: JOB-2025-000044 | F45: FALSE | M45: =IF(OR(K45="",K45>TODAY()),TODAY()-J45,K45-J45) -> 46124
A46: JOB-2025-000045 | F46: FALSE | M46: =IF(OR(K46="",K46>TODAY()),TODAY()-J46,K46-J46) -> 46124
A47: JOB-2025-000046 | F47: FALSE | M47: =IF(OR(K47="",K47>TODAY()),TODAY()-J47,K47-J47) -> 46124
A48: JOB-2025-000047 | F48: FALSE | M48: =IF(OR(K48="",K48>TODAY()),TODAY()-J48,K48-J48) -> 46124
A49: JOB-2025-000048 | F49: FALSE | M49: =IF(OR(K49="",K49>TODAY()),TODAY()-J49,K49-J49) -> 46124
A50: JOB-2025-000049 | F50: FALSE | M50: =IF(OR(K50="",K50>TODAY()),TODAY()-J50,K50-J50) -> 46124
A51: JOB-2025-000050 | F51: FALSE | M51: =IF(OR(K51="",K51>TODAY()),TODAY()-J51,K51-J51) -> 46124
A52: JOB-2025-000051 | F52: FALSE | M52: =IF(OR(K52="",K52>TODAY()),TODAY()-J52,K52-J52) -> 46124
A53: JOB-2025-000052 | F53: FALSE | M53: =IF(OR(K53="",K53>TODAY()),TODAY()-J53,K53-J53) -> 46124
... A196: JOB-2025-000195 | F196: FALSE | M196: =IF(OR(K196="",K196>TODAY()),TODAY()-J196,K196-J196) -> 46124
F197: FALSE | M197: =IF(OR(K197="",K197>TODAY()),TODAY()-J197,K197-J197) -> 46124
F198: FALSE | M198: =IF(OR(K198="",K198>TODAY()),TODAY()-J198,K198-J198) -> 46124
F199: FALSE | M199: =IF(OR(K199="",K199>TODAY()),TODAY()-J199,K199-J199) -> 46124
F200: FALSE | M200: =IF(OR(K200="",K200>TODAY()),TODAY()-J200,K200-J200) -> 46124
F201: FALSE | M201: =IF(OR(K201="",K201>TODAY()),TODAY()-J201,K201-J201) -> 46124
F202: FALSE | M202: =IF(OR(K202="",K202>TODAY()),TODAY()-J202,K202-J202) -> 46124
F203: FALSE | M203: =IF(OR(K203="",K203>TODAY()),TODAY()-J203,K203-J203) -> 46124
F204: FALSE | M204: =IF(OR(K204="",K204>TODAY()),TODAY()-J204,K204-J204) -> 46124
F205: FALSE | M205: =IF(OR(K205="",K205>TODAY()),TODAY()-J205,K205-J205) -> 46124
F206: FALSE | M206: =IF(OR(K206="",K206>TODAY()),TODAY()-J206,K206-J206) -> 46124
F207: FALSE | M207: =IF(OR(K207="",K207>TODAY()),TODAY()-J207,K207-J207) -> 46124
F208: FALSE | M208: =IF(OR(K208="",K208>TODAY()),TODAY()-J208,K208-J208) -> 46124
... F235: FALSE | M235: =IF(OR(K235="",K235>TODAY()),TODAY()-J235,K235-J235) -> 46124
F236: FALSE
F237: FALSE
F238: FALSE
F239: FALSE
F240: FALSE
F241: FALSE
F242: FALSE
F243: FALSE
F244: FALSE
F245: FALSE
F246: FALSE
F247: FALSE
... F387: FALSE
M388: =SUM(#REF!) -> #REF!

Sheet DESCRIPCION BASE
A1: id | B1: posicion | C1: Responsabilidades Principales | D1: Perfil Esperado | E1: Desafios del rol | F1: Habilidades Principales | G1: Propuesta de valor | H1: Ubicación | I1: Modalidad | J1: fechaPublicacion
A2: =BASE!A2 -> JOB-2025-000001 | B2: =BASE!B2 -> Regional Comercial | C2: ✔ Liderar el proceso de compra y venta de hacienda: Serás el punto clave en todo el proceso, desde el contacto inicial hasta la entrega final, gestionando la logística con eficiencia y asegurando que todo funcione sin problemas. ✔ Desarrollar tu zona de influencia: Serás responsable de identificar nuevas oportunidades y expandir nuestra red de clientes, contactando a aquellos que ya están en nuestros prospectos y abriendo nuevas tranqueras. ✔ Cultivar relaciones sólidas: Mantendrás una relación cercana y continua con nuestros clientes, entendiendo sus necesidades y asegurando que cada interacción resulte en una venta exitosa. ✔ Gestión eficiente del sistema: Mantendrás nuestra base de datos actualizada, asegurando que la información sea precisa y que nuestros procesos sean ágiles y efectivos. ✔ Participación activa en marketing: Serás nuestros ojos y oídos en el terreno, siendo una pieza clave en la organización y coordinación de eventos promocionales, ayudándonos a posicionarnos como líderes en el mercado. | D2: ✔ Experiencia mínima de 2 años en comercialización de hacienda bovina (gordos, invernada, cría). ✔ Sólidos conocimientos en ganadería bovina, tipos de categorías, plazos y condiciones de operación. ✔ Perfil comercial proactivo, con excelente manejo de relaciones interpersonales. ✔ Capacidad para detectar oportunidades de negocio, fidelizar clientes y generar nuevos vínculos comerciales. ✔ Conocimiento del mercado ganadero, operadores, consignatarias y zonas de producción. ✔ Autonomía para la gestión comercial integral: desde la captación de operaciones hasta el cierre y seguimiento. ✔ Disponibilidad para viajar. ✔ Se valora cartera de clientes activa o red de contactos en el sector. | E2: ✔ Desarrollar y expandir la cartera de clientes en su zona. ✔ Impulsar la adopción de soluciones digitales en el sector ganadero. ✔ Gestionar de punta a punta las operaciones comerciales. ✔ Generar relaciones de confianza con productores y clientes. ✔ Contribuir al posicionamiento de la compañía en el mercado regional. | F2: ✔Perfil comercial con orientación a resultados. ✔Capacidad de negociación y cierre. ✔Autonomía y proactividad. ✔Buen manejo de relaciones interpersonales. ✔Manejo de herramientas digitales. ✔Conocimiento del mercado ganadero (Excluyente) | H2: Corrientes - Mercedes | I2: Hibrido | J2: =BASE!J2 -> 46097
A3: =BASE!A3 -> JOB-2025-000002 | B3: =BASE!B3 -> Regional Comercial | C3: ✔ Liderar el proceso de compra y venta de hacienda: Serás el punto clave en todo el proceso, desde el contacto inicial hasta la entrega final, gestionando la logística con eficiencia y asegurando que todo funcione sin problemas. ✔ Desarrollar tu zona de influencia: Serás responsable de identificar nuevas oportunidades y expandir nuestra red de clientes, contactando a aquellos que ya están en nuestros prospectos y abriendo nuevas tranqueras. ✔ Cultivar relaciones sólidas: Mantendrás una relación cercana y continua con nuestros clientes, entendiendo sus necesidades y asegurando que cada interacción resulte en una venta exitosa. ✔ Gestión eficiente del sistema: Mantendrás nuestra base de datos actualizada, asegurando que la información sea precisa y que nuestros procesos sean ágiles y efectivos. ✔ Participación activa en marketing: Serás nuestros ojos y oídos en el terreno, siendo una pieza clave en la organización y coordinación de eventos promocionales, ayudándonos a posicionarnos como líderes en el mercado. | D3: ✔ Experiencia mínima de 2 años en comercialización de hacienda bovina (gordos, invernada, cría). Sólidos conocimientos en ganadería bovina, tipos de categorías, plazos y condiciones de operación. ✔ Perfil comercial proactivo, con excelente manejo de relaciones interpersonales. ✔ Capacidad para detectar oportunidades de negocio, fidelizar clientes y generar nuevos vínculos comerciales. ✔ Conocimiento del mercado ganadero, operadores, consignatarias y zonas de producción. ✔ Autonomía para la gestión comercial integral: desde la captación de operaciones hasta el cierre y seguimiento. ✔ Disponibilidad para viajar. ✔ Se valora cartera de clientes activa o red de contactos en el sector. | E3: ✔ Desarrollar y expandir la cartera de clientes en su zona. ✔ Impulsar la adopción de soluciones digitales en el sector ganadero. ✔ Gestionar de punta a punta las operaciones comerciales. ✔ Generar relaciones de confianza con productores y clientes. ✔ Contribuir al posicionamiento de la compañía en el mercado regional. | F3: ✔Perfil comercial con orientación a resultados. ✔Capacidad de negociación y cierre. ✔Autonomía y proactividad. ✔Buen manejo de relaciones interpersonales. ✔Manejo de herramientas digitales. ✔Conocimiento del mercado ganadero (Excluyente) | H3: La Pampa - Realico / Loventue / Rancul | I3: Hibrido | J3: =BASE!J3 -> 46097
A4: =BASE!A4 -> JOB-2025-000003 | B4: =BASE!B4 -> Regional Comercial | C4: ✔ Liderar el proceso de compra y venta de hacienda: Serás el punto clave en todo el proceso, desde el contacto inicial hasta la entrega final, gestionando la logística con eficiencia y asegurando que todo funcione sin problemas. ✔ Desarrollar tu zona de influencia: Serás responsable de identificar nuevas oportunidades y expandir nuestra red de clientes, contactando a aquellos que ya están en nuestros prospectos y abriendo nuevas tranqueras. ✔ Cultivar relaciones sólidas: Mantendrás una relación cercana y continua con nuestros clientes, entendiendo sus necesidades y asegurando que cada interacción resulte en una venta exitosa. ✔ Gestión eficiente del sistema: Mantendrás nuestra base de datos actualizada, asegurando que la información sea precisa y que nuestros procesos sean ágiles y efectivos. ✔ Participación activa en marketing: Serás nuestros ojos y oídos en el terreno, siendo una pieza clave en la organización y coordinación de eventos promocionales, ayudándonos a posicionarnos como líderes en el mercado. | D4: ✔ Experiencia mínima de 2 años en comercialización de hacienda bovina (gordos, invernada, cría). Sólidos conocimientos en ganadería bovina, tipos de categorías, plazos y condiciones de operación. ✔ Perfil comercial proactivo, con excelente manejo de relaciones interpersonales. ✔ Capacidad para detectar oportunidades de negocio, fidelizar clientes y generar nuevos vínculos comerciales. ✔ Conocimiento del mercado ganadero, operadores, consignatarias y zonas de producción. ✔ Autonomía para la gestión comercial integral: desde la captación de operaciones hasta el cierre y seguimiento. ✔ Disponibilidad para viajar. ✔ Se valora cartera de clientes activa o red de contactos en el sector. | E4: ✔ Desarrollar y expandir la cartera de clientes en su zona. ✔ Impulsar la adopción de soluciones digitales en el sector ganadero. ✔ Gestionar de punta a punta las operaciones comerciales. ✔ Generar relaciones de confianza con productores y clientes. ✔ Contribuir al posicionamiento de la compañía en el mercado regional. | F4: ✔Perfil comercial con orientación a resultados. ✔Capacidad de negociación y cierre. ✔Autonomía y proactividad. ✔Buen manejo de relaciones interpersonales. ✔Manejo de herramientas digitales. ✔Conocimiento del mercado ganadero (Excluyente) | H4: Buenos Aires - Junin | I4: Híbrido | J4: =BASE!J4 -> 46097
A5: =BASE!A5 -> JOB-2025-000004 | B5: =BASE!B5 -> Regional Comercial | C5: ✔ Liderar el proceso de compra y venta de hacienda: Serás el punto clave en todo el proceso, desde el contacto inicial hasta la entrega final, gestionando la logística con eficiencia y asegurando que todo funcione sin problemas. ✔ Desarrollar tu zona de influencia: Serás responsable de identificar nuevas oportunidades y expandir nuestra red de clientes, contactando a aquellos que ya están en nuestros prospectos y abriendo nuevas tranqueras. ✔ Cultivar relaciones sólidas: Mantendrás una relación cercana y continua con nuestros clientes, entendiendo sus necesidades y asegurando que cada interacción resulte en una venta exitosa. ✔ Gestión eficiente del sistema: Mantendrás nuestra base de datos actualizada, asegurando que la información sea precisa y que nuestros procesos sean ágiles y efectivos. ✔ Participación activa en marketing: Serás nuestros ojos y oídos en el terreno, siendo una pieza clave en la organización y coordinación de eventos promocionales, ayudándonos a posicionarnos como líderes en el mercado. | D5: ✔Experiencia mínima de 2 años en comercialización de hacienda bovina (gordos, invernada, cría). ✔Sólidos conocimientos en ganadería bovina, tipos de categorías, plazos y condiciones de operación. ✔ Perfil comercial proactivo, con excelente manejo de relaciones interpersonales. ✔ Capacidad para detectar oportunidades de negocio, fidelizar clientes y generar nuevos vínculos comerciales. ✔ Conocimiento del mercado ganadero, operadores, consignatarias y zonas de producción. ✔ Autonomía para la gestión comercial integral: desde la captación de operaciones hasta el cierre y seguimiento. ✔ Disponibilidad para viajar. ✔ Se valora cartera de clientes activa o red de contactos en el sector. | E5: ✔ Desarrollar y expandir la cartera de clientes en su zona. ✔ Impulsar la adopción de soluciones digitales en el sector ganadero. ✔ Gestionar de punta a punta las operaciones comerciales. ✔ Generar relaciones de confianza con productores y clientes. ✔ Contribuir al posicionamiento de la compañía en el mercado regional. | F5: ✔Perfil comercial con orientación a resultados. ✔Capacidad de negociación y cierre. ✔Autonomía y proactividad. ✔Buen manejo de relaciones interpersonales. ✔Manejo de herramientas digitales. ✔Conocimiento del mercado ganadero (Excluyente) | H5: Chaco - Tapenaga / Almirante Brown / Libertador General San Martin | I5: Híbrido | J5: =BASE!J5 -> 46097
A6: =BASE!A6 -> JOB-2025-000005 | B6: =BASE!B6 -> Regional Comercial | C6: ✔ Liderar el proceso de compra y venta de hacienda: Serás el punto clave en todo el proceso, desde el contacto inicial hasta la entrega final, gestionando la logística con eficiencia y asegurando que todo funcione sin problemas. ✔ Desarrollar tu zona de influencia: Serás responsable de identificar nuevas oportunidades y expandir nuestra red de clientes, contactando a aquellos que ya están en nuestros prospectos y abriendo nuevas tranqueras. ✔ Cultivar relaciones sólidas: Mantendrás una relación cercana y continua con nuestros clientes, entendiendo sus necesidades y asegurando que cada interacción resulte en una venta exitosa. ✔ Gestión eficiente del sistema: Mantendrás nuestra base de datos actualizada, asegurando que la información sea precisa y que nuestros procesos sean ágiles y efectivos. ✔ Participación activa en marketing: Serás nuestros ojos y oídos en el terreno, siendo una pieza clave en la organización y coordinación de eventos promocionales, ayudándonos a posicionarnos como líderes en el mercado. | D6: ✔ Experiencia mínima de 2 años en comercialización de hacienda bovina (gordos, invernada, cría). Sólidos conocimientos en ganadería bovina, tipos de categorías, plazos y condiciones de operación. ✔ Perfil comercial proactivo, con excelente manejo de relaciones interpersonales. ✔ Capacidad para detectar oportunidades de negocio, fidelizar clientes y generar nuevos vínculos comerciales. ✔ Conocimiento del mercado ganadero, operadores, consignatarias y zonas de producción. ✔ Autonomía para la gestión comercial integral: desde la captación de operaciones hasta el cierre y seguimiento. ✔ Disponibilidad para viajar. ✔ Se valora cartera de clientes activa o red de contactos en el sector. | E6: ✔ Desarrollar y expandir la cartera de clientes en su zona. ✔ Impulsar la adopción de soluciones digitales en el sector ganadero. ✔ Gestionar de punta a punta las operaciones comerciales. ✔ Generar relaciones de confianza con productores y clientes. ✔ Contribuir al posicionamiento de la compañía en el mercado regional. | F6: ✔Perfil comercial con orientación a resultados. ✔Capacidad de negociación y cierre. ✔Autonomía y proactividad. ✔Buen manejo de relaciones interpersonales. ✔Manejo de herramientas digitales. ✔Conocimiento del mercado ganadero (Excluyente) | H6: Santa Fe - San Cristobal / Vera | I6: Híbrido | J6: =BASE!J6 -> 46097
A7: =BASE!A7 -> JOB-2025-000006 | B7: =BASE!B7 -> Analista de Desarrollo Comercial | C7: ✔ Brindar soporte al desarrollo comercial, colaborando con distintos equipos para asegurar una gestión eficiente. ✔ Elaborar y analizar reportes para la toma de decisiones estratégicas. ✔ Identificar oportunidades de mejora en los procesos existentes y proponer soluciones innovadoras. ✔ Automatizar procesos operativos que actualmente se realizan de forma manual, contribuyendo a una mayor eficiencia y productividad. ✔ Desarrollo de KPIs y métricas. | D7: ✔ Estudiante o graduado de las carreras: Ingeniería, Administración de Empresas o afines ✔ Experiencia en posiciones similares ✔ Conocimientos en Power BI, SQL, Google Sheets, herramientas de visualización | E7: ✔Acompañar el desarrollo del área comercial con foco en eficiencia. ✔Generar información clave para la toma de decisiones. ✔Detectar oportunidades de mejora en procesos internos. ✔Impulsar la automatización de tareas operativas. ✔Desarrollar y dar seguimiento a KPIs del área. | F7: ✔Perfil analítico y orientado a resultados. ✔Manejo de herramientas de análisis de datos. ✔Capacidad de organización y planificación. ✔Proactividad y pensamiento crítico. ✔Orientación a la mejora continua. ✔Buen manejo de herramientas digitales. | G7: ✔ Prepaga de primer nivel ✔ Almuerzo en oficina sin costo ✔ Bonificación del 80% en SportClub ✔ Descuentos exclusivos en Samsung ✔ Club de beneficios | H7: =BASE!D7 -> Buenos Aires | I7: Híbrido | J7: =BASE!J7 -> 46082
A8: =BASE!A8 -> JOB-2025-000007 | B8: =BASE!B8 -> Operador Comercial de Hacienda | H8: =BASE!D8 -> Buenos Aires | I8: Hibrido | J8: =BASE!J8 -> 46097
A9: =BASE!A9 -> JOB-2025-000008 | B9: =BASE!B9 -> Analista de Legales | C9: ✔ Detectar espacios de riesgo y generar acciones preventivas como procesos, alertas, mejoras de seguridad jurídica, etc. ✔ Armar disclaimers para los productos nuevos de digitalización de operaciones, para los servicios de logística tercerizados, etc. ✔ Dar seguimiento y accionar sobre los casos de cobranzas atrasadas, tanto para detectar casos potenciales como para promover acciones de cobro, ya sea preventivas o ejecutivas, como embargos o lo que proceda según el caso. ✔ Revisar y redactar contratos con proveedores, clientes o aliados estratégicos. ✔ Colaborar en auditorías internas para asegurar cumplimiento normativo. | D9: ✔ Abogado recibido. ✔ Perfil proactivo, con iniciativa y orientación a la resolución de problemas. ✔ Capacidad de investigación y actualización constante en normativa ✔ Buen nivel de redacción y comunicación. ✔ Conocimientos en Google Sheets y herramientas de visualización ✔ Ubicación: CABA - Monserrat. ✔ Esquema Presencial. | E9: ✔Anticipar y mitigar riesgos legales en operaciones digitales y logísticas. ✔Asegurar el cumplimiento normativo en un entorno de negocios dinámico. ✔Gestionar eficientemente procesos de cobranzas con impacto legal. ✔Adaptar marcos contractuales a nuevos modelos de negocio. | F9: ✔Análisis jurídico y pensamiento crítico. ✔Redacción técnica y contractual. ✔Proactividad en la gestión de riesgos. ✔Organización y seguimiento de casos. ✔Comunicación efectiva con áreas no legales. | G9: ✔ Prepaga de primer nivel ✔ Almuerzo en oficina sin costo ✔ Bonificación del 80% en SportClub ✔ Descuentos exclusivos en Samsung ✔ Club de beneficios | H9: =BASE!D9 -> Buenos Aires | I9: Híbrido | J9: =BASE!J9 -> 46097
A10: =BASE!A10 -> JOB-2025-000009 | B10: =BASE!B10 -> Analista de Finanzas y créditos | C10: ✔ Análisis de datos, generación de métricas y reportes orientado a dar soporte y mejora continua al equipo de Finanzas y Créditos con alta injerencia en el área de Administración. ✔ Será responsable del reporting con todo lo relacionado a Cobranzas y Pagos. ✔ Estructurará refinanciaciones a compradores, definiendo plazos, tasas e importes. ✔ Dará soporte al área de administración a través de creación de herramientas/planillas para robustecer procesos y mejorar los mismos. ✔ Deberá poder entender y manejar sistemas de gestión contables para estructurar información y armar KPIs. | D10: ✔ Perfil proactivo, con ganas de aprender, iniciativa y orientación a la resolución de problemas. ✔ Conocimientos en Google Sheets y herramientas de visualización | E10: ✔Optimizar la gestión de cobranzas y pagos mediante análisis financiero. ✔Diseñar propuestas de refinanciación viables según perfil del cliente. ✔Generar información confiable para la toma de decisiones crediticias. ✔Mejorar procesos administrativos a través de herramientas de gestión. | F10: ✔Análisis financiero y manejo de datos. ✔Pensamiento analítico y resolución de problemas. ✔Organización y atención al detalle. ✔Manejo de sistemas contables y financieros. ✔Proactividad para la mejora de procesos. | G10: ✔ Prepaga de primer nivel ✔ Almuerzo en oficina sin costo ✔ Bonificación del 80% en SportClub ✔ Descuentos exclusivos en Samsung ✔ Club de beneficios | H10: =BASE!D10 -> Buenos Aires | I10: Híbrido | J10: =BASE!J10 -> 46082
A11: =BASE!A11 -> JOB-2025-000010 | B11: =BASE!B11 -> Gerente de Unidad Financiera | C11: Gestión integral del P&L del área ✓ Responsable de la facturación (top line) y de los costos asociados a dCP. Crecimiento comercial ✓ Incrementar el uso de la plataforma por parte de clientes actuales (ej. mayor cantidad de pagos por cliente). ✓ Impulsar productos existentes como anticipos y refinanciaciones comerciales. ✓ Liderar el desarrollo e implementación de nuevos productos financieros. Desarrollo de procesos ✓ Definir y estructurar procesos comerciales, de atención al cliente y de backoffice. ✓ Trabajar en coordinación con áreas transversales (Producto, Tecnología, Operaciones y Atención al Cliente). Relaciones internas clave ✓ Administración y Finanzas, para procesos internos. ✓ Planificación, Soporte y Gestión, Atención al Cliente y Transporte. ✓ Desarrollo Tecnológico (equipo de Producto y de Desarrollo). | D11: ✔ Experiencia senior (idealmente 10+ años en fintech, banca, pagos digitales, o negocios con fuerte componente financiero). ✔Capacidad probada de manejar un P&L. ✔Mentalidad emprendedora, con foco en crecimiento, desarrollo comercial y escalabilidad de procesos. ✔Habilidad para trabajar en un ecosistema de stakeholders múltiples (producto, tecnología, comercial, atención). ✔Alta orientación a resultados, con track record en lanzamiento y escalada de productos financieros. ✔Buen entendimiento de productos como factoring, lending, pagos B2B y otros instrumentos financieros. | E11: ✔Gestionar el P&L del área, asegurando el cumplimiento de objetivos de facturación y control de costos. ✔Impulsar el crecimiento comercial mediante el uso de la plataforma y el desarrollo de productos financieros. ✔Diseñar e implementar procesos comerciales, operativos y de atención al cliente. ✔Liderar iniciativas transversales junto a Producto, Tecnología y Operaciones. | F11: ✔Visión estratégica y orientación a resultados. ✔Liderazgo y gestión de equipos. ✔Desarrollo de negocio y productos financieros. ✔Mejora de procesos y coordinación interáreas. ✔Análisis financiero y toma de decisiones. | G11: ✔ Prepaga de primer nivel ✔ Almuerzo en oficina sin costo ✔ Bonificación del 80% en SportClub ✔ Descuentos exclusivos en Samsung ✔ Club de beneficios ✔Cochera sin costo | H11: =BASE!D11 -> Buenos Aires | I11: Híbrido | J11: =BASE!J11 -> 46097
A12: =BASE!A12 -> JOB-2025-000011 | B12: =BASE!B12 -> Analista de Operaciones Comerciales | C12: ✔ Relevar y documentar procesos comerciales actuales, identificando oportunidades de optimización. ✔ Diseñar e implementar mejoras en los flujos y herramientas de gestión comercial (CRM, reportes, tableros, etc.). ✔ Extraer y limpiar datos de diversas fuentes (SQL, Excel, sistemas internos). ✔ Construir dashboards e informes en Power BI u otras herramientas de visualización. ✔ Diseñar y mantener indicadores clave (KPIs) que midan la efectividad y rentabilidad de las acciones comerciales. ✔ Analizar tendencias y comportamientos del negocio para generar insights que impacten en la estrategia comercial. ✔ Dar soporte analítico a las unidades de negocio, asegurando la consistencia de la información. | D12: ✔ Graduados de las carreras de Ingeniería Industrial. Adm de empresas, Adm Agropecuaria, similares. ✔ Manejo de Google Sheets, SQL y Power BI. ✔ Interés en la innovación tecnológica y la automatización de procesos. ✔ Actitud proactiva y resolutiva, con orientación a resultados. | E12: ✔Analizar y optimizar los procesos comerciales para mejorar la eficiencia operativa. ✔Transformar datos en información accionable para la toma de decisiones. ✔Diseñar y monitorear KPIs que permitan evaluar la performance del negocio. ✔Brindar soporte analítico a las distintas unidades comerciales. | F12: ✔Pensamiento analítico y orientación a resultados. ✔Manejo de herramientas de análisis de datos (SQL, Excel, BI). ✔Mejora de procesos y gestión de indicadores. ✔Capacidad de organización y trabajo transversal. ✔Comunicación efectiva para la interpretación de insights. | G12: ✔ Prepaga de primer nivel ✔ Almuerzo en oficina sin costo ✔ Bonificación del 80% en SportClub ✔ Descuentos exclusivos en Samsung ✔ Club de beneficios | H12: =BASE!D12 -> Buenos Aires | I12: Híbrido | J12: =BASE!J12 -> 46097
A13: =BASE!A13 -> JOB-2025-000012 | B13: =BASE!B13 -> Analista Contable SR | C13: ✔ Gestionar la operatoria administrativa diaria del área, asegurando orden y seguimiento de los distintos procesos. ✔ Registrar asientos contables y mantener la información contable actualizada. ✔ Realizar conciliaciones de cuentas contables y bancarias, identificando y siguiendo partidas pendientes. ✔ Analizar información contable y financiera, detectando desvíos y oportunidades de mejora. ✔ Llevar de manera metódica y organizada las partidas conciliatorias y reportes en Google Sheets. ✔ Administrar y dar seguimiento a temas vinculados a: ● Flota de la empresa ● Suministros ● Pagos y cobros ● Inversiones y otros procesos administrativos del sector | D13: ✔ Estudiante de la carrera de Contador. ✔ Manejo de Google Sheets, ✔Capacidad para trabajar de forma colaborativa, interactuando con distintos equipos ✔Perfil orientado a la mejora continua ✔Pensamiento lógico, analítico y resolutivo | F13: Analitico ,Comunicación Efectiva,Escucha Activa | G13: ✔ Prepaga de primer nivel ✔ Almuerzo en oficina sin costo ✔ Bonificación del 80% en SportClub ✔ Descuentos exclusivos en Samsung ✔ Club de beneficios | H13: =BASE!D13 -> Buenos Aires | I13: Híbrido | J13: =BASE!J13 -> 46002
A14: =BASE!A14 -> JOB-2025-000013 | B14: =BASE!B14 -> Analista de At. al Cliente | H14: =BASE!D14 -> Buenos Aires | I14: Hibrido | J14: =BASE!J14 -> 46082
A15: =BASE!A15 -> JOB-2025-000014 | B15: =BASE!B15 -> Analista de Logistica | H15: =BASE!D15 -> Buenos Aires | I15: Hibrido | J15: =BASE!J15 -> 46082
A16: =BASE!A16 -> JOB-2025-000015 | B16: =BASE!B16 -> Pasante Machine Learning | H16: =BASE!D16 -> Buenos Aires | I16: Hibrido | J16: =BASE!J16 -> 46082
A17: =BASE!A17 -> JOB-2025-000016 | B17: =BASE!B17 -> Regional Comercial | C17: ✔ Liderar el proceso de compra y venta de hacienda: Serás el punto clave en todo el proceso, desde el contacto inicial hasta la entrega final, gestionando la logística con eficiencia y asegurando que todo funcione sin problemas. ✔ Desarrollar tu zona de influencia: Serás responsable de identificar nuevas oportunidades y expandir nuestra red de clientes, contactando a aquellos que ya están en nuestros prospectos y abriendo nuevas tranqueras. ✔ Cultivar relaciones sólidas: Mantendrás una relación cercana y continua con nuestros clientes, entendiendo sus necesidades y asegurando que cada interacción resulte en una venta exitosa. ✔ Gestión eficiente del sistema: Mantendrás nuestra base de datos actualizada, asegurando que la información sea precisa y que nuestros procesos sean ágiles y efectivos. ✔ Participación activa en marketing: Serás nuestros ojos y oídos en el terreno, siendo una pieza clave en la organización y coordinación de eventos promocionales, ayudándonos a posicionarnos como líderes en el mercado. | D17: ✔ Experiencia mínima de 2 años en comercialización de hacienda bovina (gordos, invernada, cría). ✔ Sólidos conocimientos en ganadería bovina, tipos de categorías, plazos y condiciones de operación. ✔ Perfil comercial proactivo, con excelente manejo de relaciones interpersonales. ✔ Capacidad para detectar oportunidades de negocio, fidelizar clientes y generar nuevos vínculos comerciales. ✔ Conocimiento del mercado ganadero, operadores, consignatarias y zonas de producción. ✔ Autonomía para la gestión comercial integral: desde la captación de operaciones hasta el cierre y seguimiento. ✔ Disponibilidad para viajar. ✔ Se valora cartera de clientes activa o red de contactos en el sector. | E17: ✔ Desarrollar y expandir la cartera de clientes en su zona. ✔ Impulsar la adopción de soluciones digitales en el sector ganadero. ✔ Gestionar de punta a punta las operaciones comerciales. ✔ Generar relaciones de confianza con productores y clientes. ✔ Contribuir al posicionamiento de la compañía en el mercado regional. | F17: ✔Perfil comercial con orientación a resultados. ✔Capacidad de negociación y cierre. ✔Autonomía y proactividad. ✔Buen manejo de relaciones interpersonales. ✔Manejo de herramientas digitales. ✔Conocimiento del mercado ganadero (Excluyente) | H17: Buenos Aires - Pergamino / Rojas | I17: Híbrido | J17: =BASE!J17 -> 46097
A18: =BASE!A18 -> JOB-2025-000017 | B18: =BASE!B18 -> Regional Comercial | C18: ✔ Liderar el proceso de compra y venta de hacienda: Serás el punto clave en todo el proceso, desde el contacto inicial hasta la entrega final, gestionando la logística con eficiencia y asegurando que todo funcione sin problemas. ✔ Desarrollar tu zona de influencia: Serás responsable de identificar nuevas oportunidades y expandir nuestra red de clientes, contactando a aquellos que ya están en nuestros prospectos y abriendo nuevas tranqueras. ✔ Cultivar relaciones sólidas: Mantendrás una relación cercana y continua con nuestros clientes, entendiendo sus necesidades y asegurando que cada interacción resulte en una venta exitosa. ✔ Gestión eficiente del sistema: Mantendrás nuestra base de datos actualizada, asegurando que la información sea precisa y que nuestros procesos sean ágiles y efectivos. ✔ Participación activa en marketing: Serás nuestros ojos y oídos en el terreno, siendo una pieza clave en la organización y coordinación de eventos promocionales, ayudándonos a posicionarnos como líderes en el mercado. | D18: ✔ Experiencia mínima de 2 años en comercialización de hacienda bovina (gordos, invernada, cría). Sólidos conocimientos en ganadería bovina, tipos de categorías, plazos y condiciones de operación. ✔ Perfil comercial proactivo, con excelente manejo de relaciones interpersonales. ✔ Capacidad para detectar oportunidades de negocio, fidelizar clientes y generar nuevos vínculos comerciales. ✔ Conocimiento del mercado ganadero, operadores, consignatarias y zonas de producción. ✔ Autonomía para la gestión comercial integral: desde la captación de operaciones hasta el cierre y seguimiento. ✔ Disponibilidad para viajar. ✔ Se valora cartera de clientes activa o red de contactos en el sector. | E18: ✔ Desarrollar y expandir la cartera de clientes en su zona. ✔ Impulsar la adopción de soluciones digitales en el sector ganadero. ✔ Gestionar de punta a punta las operaciones comerciales. ✔ Generar relaciones de confianza con productores y clientes. ✔ Contribuir al posicionamiento de la compañía en el mercado regional. | F18: ✔Perfil comercial con orientación a resultados. ✔Capacidad de negociación y cierre. ✔Autonomía y proactividad. ✔Buen manejo de relaciones interpersonales. ✔Manejo de herramientas digitales. ✔Conocimiento del mercado ganadero (Excluyente) | H18: Santa Fe - 9 de Julio | I18: Híbrido | J18: =BASE!J18 -> 46097
A19: =BASE!A19 -> JOB-2025-000018 | B19: =BASE!B19 -> Regional Comercial | C19: ✔ Liderar el proceso de compra y venta de hacienda: Serás el punto clave en todo el proceso, desde el contacto inicial hasta la entrega final, gestionando la logística con eficiencia y asegurando que todo funcione sin problemas. ✔ Desarrollar tu zona de influencia: Serás responsable de identificar nuevas oportunidades y expandir nuestra red de clientes, contactando a aquellos que ya están en nuestros prospectos y abriendo nuevas tranqueras. ✔ Cultivar relaciones sólidas: Mantendrás una relación cercana y continua con nuestros clientes, entendiendo sus necesidades y asegurando que cada interacción resulte en una venta exitosa. ✔ Gestión eficiente del sistema: Mantendrás nuestra base de datos actualizada, asegurando que la información sea precisa y que nuestros procesos sean ágiles y efectivos. ✔ Participación activa en marketing: Serás nuestros ojos y oídos en el terreno, siendo una pieza clave en la organización y coordinación de eventos promocionales, ayudándonos a posicionarnos como líderes en el mercado. | D19: ✔ Experiencia mínima de 2 años en comercialización de hacienda bovina (gordos, invernada, cría). Sólidos conocimientos en ganadería bovina, tipos de categorías, plazos y condiciones de operación. ✔ Perfil comercial proactivo, con excelente manejo de relaciones interpersonales. ✔ Capacidad para detectar oportunidades de negocio, fidelizar clientes y generar nuevos vínculos comerciales. ✔ Conocimiento del mercado ganadero, operadores, consignatarias y zonas de producción. ✔ Autonomía para la gestión comercial integral: desde la captación de operaciones hasta el cierre y seguimiento. ✔ Disponibilidad para viajar. ✔ Se valora cartera de clientes activa o red de contactos en el sector. | E19: ✔ Desarrollar y expandir la cartera de clientes en su zona. ✔ Impulsar la adopción de soluciones digitales en el sector ganadero. ✔ Gestionar de punta a punta las operaciones comerciales. ✔ Generar relaciones de confianza con productores y clientes. ✔ Contribuir al posicionamiento de la compañía en el mercado regional. | F19: ✔Perfil comercial con orientación a resultados. ✔Capacidad de negociación y cierre. ✔Autonomía y proactividad. ✔Buen manejo de relaciones interpersonales. ✔Manejo de herramientas digitales. ✔Conocimiento del mercado ganadero (Excluyente) | H19: Entre Rios - Villaguay | I19: Híbrido | J19: =BASE!J20 -> 46097
A20: =BASE!A20 -> JOB-2025-000019 | B20: =BASE!B20 -> Regional Comercial | C20: ✔ Liderar el proceso de compra y venta de hacienda: Serás el punto clave en todo el proceso, desde el contacto inicial hasta la entrega final, gestionando la logística con eficiencia y asegurando que todo funcione sin problemas. ✔ Desarrollar tu zona de influencia: Serás responsable de identificar nuevas oportunidades y expandir nuestra red de clientes, contactando a aquellos que ya están en nuestros prospectos y abriendo nuevas tranqueras. ✔ Cultivar relaciones sólidas: Mantendrás una relación cercana y continua con nuestros clientes, entendiendo sus necesidades y asegurando que cada interacción resulte en una venta exitosa. ✔ Gestión eficiente del sistema: Mantendrás nuestra base de datos actualizada, asegurando que la información sea precisa y que nuestros procesos sean ágiles y efectivos. ✔ Participación activa en marketing: Serás nuestros ojos y oídos en el terreno, siendo una pieza clave en la organización y coordinación de eventos promocionales, ayudándonos a posicionarnos como líderes en el mercado. | D20: ✔ Experiencia mínima de 2 años en comercialización de hacienda bovina (gordos, invernada, cría). Sólidos conocimientos en ganadería bovina, tipos de categorías, plazos y condiciones de operación. ✔ Perfil comercial proactivo, con excelente manejo de relaciones interpersonales. ✔ Capacidad para detectar oportunidades de negocio, fidelizar clientes y generar nuevos vínculos comerciales. ✔ Conocimiento del mercado ganadero, operadores, consignatarias y zonas de producción. ✔ Autonomía para la gestión comercial integral: desde la captación de operaciones hasta el cierre y seguimiento. ✔ Disponibilidad para viajar. ✔ Se valora cartera de clientes activa o red de contactos en el sector. | E20: ✔ Desarrollar y expandir la cartera de clientes en su zona. ✔ Impulsar la adopción de soluciones digitales en el sector ganadero. ✔ Gestionar de punta a punta las operaciones comerciales. ✔ Generar relaciones de confianza con productores y clientes. ✔ Contribuir al posicionamiento de la compañía en el mercado regional. | F20: ✔Perfil comercial con orientación a resultados. ✔Capacidad de negociación y cierre. ✔Autonomía y proactividad. ✔Buen manejo de relaciones interpersonales. ✔Manejo de herramientas digitales. ✔Conocimiento del mercado ganadero (Excluyente) | H20: Entre Rios - Gualeguay | I20: Híbrido | J20: =BASE!J21 -> 46097
A21: =BASE!A21 -> JOB-2025-000020 | B21: =BASE!B21 -> Regional Comercial | C21: ✔ Liderar el proceso de compra y venta de hacienda: Serás el punto clave en todo el proceso, desde el contacto inicial hasta la entrega final, gestionando la logística con eficiencia y asegurando que todo funcione sin problemas. ✔ Desarrollar tu zona de influencia: Serás responsable de identificar nuevas oportunidades y expandir nuestra red de clientes, contactando a aquellos que ya están en nuestros prospectos y abriendo nuevas tranqueras. ✔ Cultivar relaciones sólidas: Mantendrás una relación cercana y continua con nuestros clientes, entendiendo sus necesidades y asegurando que cada interacción resulte en una venta exitosa. ✔ Gestión eficiente del sistema: Mantendrás nuestra base de datos actualizada, asegurando que la información sea precisa y que nuestros procesos sean ágiles y efectivos. ✔ Participación activa en marketing: Serás nuestros ojos y oídos en el terreno, siendo una pieza clave en la organización y coordinación de eventos promocionales, ayudándonos a posicionarnos como líderes en el mercado. | D21: ✔ Experiencia mínima de 2 años en comercialización de hacienda bovina (gordos, invernada, cría). Sólidos conocimientos en ganadería bovina, tipos de categorías, plazos y condiciones de operación. ✔ Perfil comercial proactivo, con excelente manejo de relaciones interpersonales. ✔ Capacidad para detectar oportunidades de negocio, fidelizar clientes y generar nuevos vínculos comerciales. ✔ Conocimiento del mercado ganadero, operadores, consignatarias y zonas de producción. ✔ Autonomía para la gestión comercial integral: desde la captación de operaciones hasta el cierre y seguimiento. ✔ Disponibilidad para viajar. ✔ Se valora cartera de clientes activa o red de contactos en el sector. | E21: ✔ Desarrollar y expandir la cartera de clientes en su zona. ✔ Impulsar la adopción de soluciones digitales en el sector ganadero. ✔ Gestionar de punta a punta las operaciones comerciales. ✔ Generar relaciones de confianza con productores y clientes. ✔ Contribuir al posicionamiento de la compañía en el mercado regional. | F21: ✔Perfil comercial con orientación a resultados. ✔Capacidad de negociación y cierre. ✔Autonomía y proactividad. ✔Buen manejo de relaciones interpersonales. ✔Manejo de herramientas digitales. ✔Conocimiento del mercado ganadero (Excluyente) | H21: Cordoba - Rio Cuarto | I21: Híbrido | J21: =#REF! -> #REF!
A22: =BASE!A22 -> JOB-2025-000021 | B22: =BASE!B22 -> Regional Comercial | C22: ✔ Liderar el proceso de compra y venta de hacienda: Serás el punto clave en todo el proceso, desde el contacto inicial hasta la entrega final, gestionando la logística con eficiencia y asegurando que todo funcione sin problemas. ✔ Desarrollar tu zona de influencia: Serás responsable de identificar nuevas oportunidades y expandir nuestra red de clientes, contactando a aquellos que ya están en nuestros prospectos y abriendo nuevas tranqueras. ✔ Cultivar relaciones sólidas: Mantendrás una relación cercana y continua con nuestros clientes, entendiendo sus necesidades y asegurando que cada interacción resulte en una venta exitosa. ✔ Gestión eficiente del sistema: Mantendrás nuestra base de datos actualizada, asegurando que la información sea precisa y que nuestros procesos sean ágiles y efectivos. ✔ Participación activa en marketing: Serás nuestros ojos y oídos en el terreno, siendo una pieza clave en la organización y coordinación de eventos promocionales, ayudándonos a posicionarnos como líderes en el mercado. | D22: ✔ Experiencia mínima de 2 años en comercialización de hacienda bovina (gordos, invernada, cría). Sólidos conocimientos en ganadería bovina, tipos de categorías, plazos y condiciones de operación. ✔ Perfil comercial proactivo, con excelente manejo de relaciones interpersonales. ✔ Capacidad para detectar oportunidades de negocio, fidelizar clientes y generar nuevos vínculos comerciales. ✔ Conocimiento del mercado ganadero, operadores, consignatarias y zonas de producción. ✔ Autonomía para la gestión comercial integral: desde la captación de operaciones hasta el cierre y seguimiento. ✔ Disponibilidad para viajar. ✔ Se valora cartera de clientes activa o red de contactos en el sector. | E22: ✔ Desarrollar y expandir la cartera de clientes en su zona. ✔ Impulsar la adopción de soluciones digitales en el sector ganadero. ✔ Gestionar de punta a punta las operaciones comerciales. ✔ Generar relaciones de confianza con productores y clientes. ✔ Contribuir al posicionamiento de la compañía en el mercado regional. | F22: ✔Perfil comercial con orientación a resultados. ✔Capacidad de negociación y cierre. ✔Autonomía y proactividad. ✔Buen manejo de relaciones interpersonales. ✔Manejo de herramientas digitales. ✔Conocimiento del mercado ganadero (Excluyente) | H22: Salta - Anta | I22: Híbrido | J22: =BASE!J22 -> 46097
A23: =BASE!A23 -> JOB-2025-000022 | B23: =BASE!B23 -> Regional Comercial | C23: ✔ Liderar el proceso de compra y venta de hacienda: Serás el punto clave en todo el proceso, desde el contacto inicial hasta la entrega final, gestionando la logística con eficiencia y asegurando que todo funcione sin problemas. ✔ Desarrollar tu zona de influencia: Serás responsable de identificar nuevas oportunidades y expandir nuestra red de clientes, contactando a aquellos que ya están en nuestros prospectos y abriendo nuevas tranqueras. ✔ Cultivar relaciones sólidas: Mantendrás una relación cercana y continua con nuestros clientes, entendiendo sus necesidades y asegurando que cada interacción resulte en una venta exitosa. ✔ Gestión eficiente del sistema: Mantendrás nuestra base de datos actualizada, asegurando que la información sea precisa y que nuestros procesos sean ágiles y efectivos. ✔ Participación activa en marketing: Serás nuestros ojos y oídos en el terreno, siendo una pieza clave en la organización y coordinación de eventos promocionales, ayudándonos a posicionarnos como líderes en el mercado. | D23: ✔ Experiencia mínima de 2 años en comercialización de hacienda bovina (gordos, invernada, cría). Sólidos conocimientos en ganadería bovina, tipos de categorías, plazos y condiciones de operación. ✔ Perfil comercial proactivo, con excelente manejo de relaciones interpersonales. ✔ Capacidad para detectar oportunidades de negocio, fidelizar clientes y generar nuevos vínculos comerciales. ✔ Conocimiento del mercado ganadero, operadores, consignatarias y zonas de producción. ✔ Autonomía para la gestión comercial integral: desde la captación de operaciones hasta el cierre y seguimiento. ✔ Disponibilidad para viajar. ✔ Se valora cartera de clientes activa o red de contactos en el sector. | E23: ✔ Desarrollar y expandir la cartera de clientes en su zona. ✔ Impulsar la adopción de soluciones digitales en el sector ganadero. ✔ Gestionar de punta a punta las operaciones comerciales. ✔ Generar relaciones de confianza con productores y clientes. ✔ Contribuir al posicionamiento de la compañía en el mercado regional. | F23: ✔Perfil comercial con orientación a resultados. ✔Capacidad de negociación y cierre. ✔Autonomía y proactividad. ✔Buen manejo de relaciones interpersonales. ✔Manejo de herramientas digitales. ✔Conocimiento del mercado ganadero (Excluyente) | H23: Formosa - Patiño | I23: Híbrido | J23: =BASE!J23 -> 46097
A24: =BASE!A24 -> JOB-2025-000023 | B24: =BASE!B24 -> Regional Comercial | C24: ✔ Liderar el proceso de compra y venta de hacienda: Serás el punto clave en todo el proceso, desde el contacto inicial hasta la entrega final, gestionando la logística con eficiencia y asegurando que todo funcione sin problemas. ✔ Desarrollar tu zona de influencia: Serás responsable de identificar nuevas oportunidades y expandir nuestra red de clientes, contactando a aquellos que ya están en nuestros prospectos y abriendo nuevas tranqueras. ✔ Cultivar relaciones sólidas: Mantendrás una relación cercana y continua con nuestros clientes, entendiendo sus necesidades y asegurando que cada interacción resulte en una venta exitosa. ✔ Gestión eficiente del sistema: Mantendrás nuestra base de datos actualizada, asegurando que la información sea precisa y que nuestros procesos sean ágiles y efectivos. ✔ Participación activa en marketing: Serás nuestros ojos y oídos en el terreno, siendo una pieza clave en la organización y coordinación de eventos promocionales, ayudándonos a posicionarnos como líderes en el mercado. | D24: ✔ Experiencia mínima de 2 años en comercialización de hacienda bovina (gordos, invernada, cría). Sólidos conocimientos en ganadería bovina, tipos de categorías, plazos y condiciones de operación. ✔ Perfil comercial proactivo, con excelente manejo de relaciones interpersonales. ✔ Capacidad para detectar oportunidades de negocio, fidelizar clientes y generar nuevos vínculos comerciales. ✔ Conocimiento del mercado ganadero, operadores, consignatarias y zonas de producción. ✔ Autonomía para la gestión comercial integral: desde la captación de operaciones hasta el cierre y seguimiento. ✔ Disponibilidad para viajar. ✔ Se valora cartera de clientes activa o red de contactos en el sector. | E24: ✔ Desarrollar y expandir la cartera de clientes en su zona. ✔ Impulsar la adopción de soluciones digitales en el sector ganadero. ✔ Gestionar de punta a punta las operaciones comerciales. ✔ Generar relaciones de confianza con productores y clientes. ✔ Contribuir al posicionamiento de la compañía en el mercado regional. | F24: ✔Perfil comercial con orientación a resultados. ✔Capacidad de negociación y cierre. ✔Autonomía y proactividad. ✔Buen manejo de relaciones interpersonales. ✔Manejo de herramientas digitales. ✔Conocimiento del mercado ganadero (Excluyente) | H24: San Luis - Gobenador Dupuy | I24: Híbrido | J24: =BASE!J24 -> 46097
A25: =BASE!A25 -> JOB-2025-000024 | B25: =BASE!B25 -> Regional Comercial | C25: ✔ Liderar el proceso de compra y venta de hacienda: Serás el punto clave en todo el proceso, desde el contacto inicial hasta la entrega final, gestionando la logística con eficiencia y asegurando que todo funcione sin problemas. ✔ Desarrollar tu zona de influencia: Serás responsable de identificar nuevas oportunidades y expandir nuestra red de clientes, contactando a aquellos que ya están en nuestros prospectos y abriendo nuevas tranqueras. ✔ Cultivar relaciones sólidas: Mantendrás una relación cercana y continua con nuestros clientes, entendiendo sus necesidades y asegurando que cada interacción resulte en una venta exitosa. ✔ Gestión eficiente del sistema: Mantendrás nuestra base de datos actualizada, asegurando que la información sea precisa y que nuestros procesos sean ágiles y efectivos. ✔ Participación activa en marketing: Serás nuestros ojos y oídos en el terreno, siendo una pieza clave en la organización y coordinación de eventos promocionales, ayudándonos a posicionarnos como líderes en el mercado. | D25: ✔ Experiencia mínima de 2 años en comercialización de hacienda bovina (gordos, invernada, cría). Sólidos conocimientos en ganadería bovina, tipos de categorías, plazos y condiciones de operación. ✔ Perfil comercial proactivo, con excelente manejo de relaciones interpersonales. ✔ Capacidad para detectar oportunidades de negocio, fidelizar clientes y generar nuevos vínculos comerciales. ✔ Conocimiento del mercado ganadero, operadores, consignatarias y zonas de producción. ✔ Autonomía para la gestión comercial integral: desde la captación de operaciones hasta el cierre y seguimiento. ✔ Disponibilidad para viajar. ✔ Se valora cartera de clientes activa o red de contactos en el sector. | E25: ✔ Desarrollar y expandir la cartera de clientes en su zona. ✔ Impulsar la adopción de soluciones digitales en el sector ganadero. ✔ Gestionar de punta a punta las operaciones comerciales. ✔ Generar relaciones de confianza con productores y clientes. ✔ Contribuir al posicionamiento de la compañía en el mercado regional. | F25: ✔Perfil comercial con orientación a resultados. ✔Capacidad de negociación y cierre. ✔Autonomía y proactividad. ✔Buen manejo de relaciones interpersonales. ✔Manejo de herramientas digitales. ✔Conocimiento del mercado ganadero (Excluyente) | H25: Buenos Aires - Tapalque / Bolivar | I25: Híbrido | J25: =BASE!J25 -> 46097
A26: =BASE!A26 -> JOB-2025-000025 | B26: =BASE!B26 -> Regional Comercial | C26: ✔ Liderar el proceso de compra y venta de hacienda: Serás el punto clave en todo el proceso, desde el contacto inicial hasta la entrega final, gestionando la logística con eficiencia y asegurando que todo funcione sin problemas. ✔ Desarrollar tu zona de influencia: Serás responsable de identificar nuevas oportunidades y expandir nuestra red de clientes, contactando a aquellos que ya están en nuestros prospectos y abriendo nuevas tranqueras. ✔ Cultivar relaciones sólidas: Mantendrás una relación cercana y continua con nuestros clientes, entendiendo sus necesidades y asegurando que cada interacción resulte en una venta exitosa. ✔ Gestión eficiente del sistema: Mantendrás nuestra base de datos actualizada, asegurando que la información sea precisa y que nuestros procesos sean ágiles y efectivos. ✔ Participación activa en marketing: Serás nuestros ojos y oídos en el terreno, siendo una pieza clave en la organización y coordinación de eventos promocionales, ayudándonos a posicionarnos como líderes en el mercado. | D26: ✔ Experiencia mínima de 2 años en comercialización de hacienda bovina (gordos, invernada, cría). Sólidos conocimientos en ganadería bovina, tipos de categorías, plazos y condiciones de operación. ✔ Perfil comercial proactivo, con excelente manejo de relaciones interpersonales. ✔ Capacidad para detectar oportunidades de negocio, fidelizar clientes y generar nuevos vínculos comerciales. ✔ Conocimiento del mercado ganadero, operadores, consignatarias y zonas de producción. ✔ Autonomía para la gestión comercial integral: desde la captación de operaciones hasta el cierre y seguimiento. ✔ Disponibilidad para viajar. ✔ Se valora cartera de clientes activa o red de contactos en el sector. | E26: ✔ Desarrollar y expandir la cartera de clientes en su zona. ✔ Impulsar la adopción de soluciones digitales en el sector ganadero. ✔ Gestionar de punta a punta las operaciones comerciales. ✔ Generar relaciones de confianza con productores y clientes. ✔ Contribuir al posicionamiento de la compañía en el mercado regional. | F26: ✔Perfil comercial con orientación a resultados. ✔Capacidad de negociación y cierre. ✔Autonomía y proactividad. ✔Buen manejo de relaciones interpersonales. ✔Manejo de herramientas digitales. ✔Conocimiento del mercado ganadero (Excluyente) | H26: Buenos Aires - Azul | I26: Híbrido | J26: =BASE!J26 -> 46097
A27: =BASE!A27 -> JOB-2025-000026 | B27: =BASE!B27 -> Regional Comercial | C27: ✔ Liderar el proceso de compra y venta de hacienda: Serás el punto clave en todo el proceso, desde el contacto inicial hasta la entrega final, gestionando la logística con eficiencia y asegurando que todo funcione sin problemas. ✔ Desarrollar tu zona de influencia: Serás responsable de identificar nuevas oportunidades y expandir nuestra red de clientes, contactando a aquellos que ya están en nuestros prospectos y abriendo nuevas tranqueras. ✔ Cultivar relaciones sólidas: Mantendrás una relación cercana y continua con nuestros clientes, entendiendo sus necesidades y asegurando que cada interacción resulte en una venta exitosa. ✔ Gestión eficiente del sistema: Mantendrás nuestra base de datos actualizada, asegurando que la información sea precisa y que nuestros procesos sean ágiles y efectivos. ✔ Participación activa en marketing: Serás nuestros ojos y oídos en el terreno, siendo una pieza clave en la organización y coordinación de eventos promocionales, ayudándonos a posicionarnos como líderes en el mercado. | D27: ✔ Experiencia mínima de 2 años en comercialización de hacienda bovina (gordos, invernada, cría). Sólidos conocimientos en ganadería bovina, tipos de categorías, plazos y condiciones de operación. ✔ Perfil comercial proactivo, con excelente manejo de relaciones interpersonales. ✔ Capacidad para detectar oportunidades de negocio, fidelizar clientes y generar nuevos vínculos comerciales. ✔ Conocimiento del mercado ganadero, operadores, consignatarias y zonas de producción. ✔ Autonomía para la gestión comercial integral: desde la captación de operaciones hasta el cierre y seguimiento. ✔ Disponibilidad para viajar. ✔ Se valora cartera de clientes activa o red de contactos en el sector. | E27: ✔ Desarrollar y expandir la cartera de clientes en su zona. ✔ Impulsar la adopción de soluciones digitales en el sector ganadero. ✔ Gestionar de punta a punta las operaciones comerciales. ✔ Generar relaciones de confianza con productores y clientes. ✔ Contribuir al posicionamiento de la compañía en el mercado regional. | F27: ✔Perfil comercial con orientación a resultados. ✔Capacidad de negociación y cierre. ✔Autonomía y proactividad. ✔Buen manejo de relaciones interpersonales. ✔Manejo de herramientas digitales. ✔Conocimiento del mercado ganadero (Excluyente) | H27: Buenos Aires - General Alvear / 25 de mayo / Saladillo | I27: Híbrido | J27: =BASE!J27 -> 46097
A28: =BASE!A28 -> JOB-2025-000027 | B28: =BASE!B28 -> Regional Comercial | C28: ✔ Liderar el proceso de compra y venta de hacienda: Serás el punto clave en todo el proceso, desde el contacto inicial hasta la entrega final, gestionando la logística con eficiencia y asegurando que todo funcione sin problemas. ✔ Desarrollar tu zona de influencia: Serás responsable de identificar nuevas oportunidades y expandir nuestra red de clientes, contactando a aquellos que ya están en nuestros prospectos y abriendo nuevas tranqueras. ✔ Cultivar relaciones sólidas: Mantendrás una relación cercana y continua con nuestros clientes, entendiendo sus necesidades y asegurando que cada interacción resulte en una venta exitosa. ✔ Gestión eficiente del sistema: Mantendrás nuestra base de datos actualizada, asegurando que la información sea precisa y que nuestros procesos sean ágiles y efectivos. ✔ Participación activa en marketing: Serás nuestros ojos y oídos en el terreno, siendo una pieza clave en la organización y coordinación de eventos promocionales, ayudándonos a posicionarnos como líderes en el mercado. | D28: ✔ Experiencia mínima de 2 años en comercialización de hacienda bovina (gordos, invernada, cría). Sólidos conocimientos en ganadería bovina, tipos de categorías, plazos y condiciones de operación. ✔ Perfil comercial proactivo, con excelente manejo de relaciones interpersonales. ✔ Capacidad para detectar oportunidades de negocio, fidelizar clientes y generar nuevos vínculos comerciales. ✔ Conocimiento del mercado ganadero, operadores, consignatarias y zonas de producción. ✔ Autonomía para la gestión comercial integral: desde la captación de operaciones hasta el cierre y seguimiento. ✔ Disponibilidad para viajar. ✔ Se valora cartera de clientes activa o red de contactos en el sector. | E28: ✔ Desarrollar y expandir la cartera de clientes en su zona. ✔ Impulsar la adopción de soluciones digitales en el sector ganadero. ✔ Gestionar de punta a punta las operaciones comerciales. ✔ Generar relaciones de confianza con productores y clientes. ✔ Contribuir al posicionamiento de la compañía en el mercado regional. | F28: ✔Perfil comercial con orientación a resultados. ✔Capacidad de negociación y cierre. ✔Autonomía y proactividad. ✔Buen manejo de relaciones interpersonales. ✔Manejo de herramientas digitales. ✔Conocimiento del mercado ganadero (Excluyente) | H28: Buenos Aires - Carlos Tejedor / Florentino Ameghino / General Villegas / Rivadavia / Trenque Lauquen | I28: Híbrido | J28: =BASE!J28 -> 46097
A29: =BASE!A29 -> JOB-2025-000028 | B29: =BASE!B29 -> Regional Comercial | C29: ✔ Liderar el proceso de compra y venta de hacienda: Serás el punto clave en todo el proceso, desde el contacto inicial hasta la entrega final, gestionando la logística con eficiencia y asegurando que todo funcione sin problemas. ✔ Desarrollar tu zona de influencia: Serás responsable de identificar nuevas oportunidades y expandir nuestra red de clientes, contactando a aquellos que ya están en nuestros prospectos y abriendo nuevas tranqueras. ✔ Cultivar relaciones sólidas: Mantendrás una relación cercana y continua con nuestros clientes, entendiendo sus necesidades y asegurando que cada interacción resulte en una venta exitosa. ✔ Gestión eficiente del sistema: Mantendrás nuestra base de datos actualizada, asegurando que la información sea precisa y que nuestros procesos sean ágiles y efectivos. ✔ Participación activa en marketing: Serás nuestros ojos y oídos en el terreno, siendo una pieza clave en la organización y coordinación de eventos promocionales, ayudándonos a posicionarnos como líderes en el mercado. | D29: ✔ Experiencia mínima de 2 años en comercialización de hacienda bovina (gordos, invernada, cría). Sólidos conocimientos en ganadería bovina, tipos de categorías, plazos y condiciones de operación. ✔ Perfil comercial proactivo, con excelente manejo de relaciones interpersonales. ✔ Capacidad para detectar oportunidades de negocio, fidelizar clientes y generar nuevos vínculos comerciales. ✔ Conocimiento del mercado ganadero, operadores, consignatarias y zonas de producción. ✔ Autonomía para la gestión comercial integral: desde la captación de operaciones hasta el cierre y seguimiento. ✔ Disponibilidad para viajar. ✔ Se valora cartera de clientes activa o red de contactos en el sector. | E29: ✔ Desarrollar y expandir la cartera de clientes en su zona. ✔ Impulsar la adopción de soluciones digitales en el sector ganadero. ✔ Gestionar de punta a punta las operaciones comerciales. ✔ Generar relaciones de confianza con productores y clientes. ✔ Contribuir al posicionamiento de la compañía en el mercado regional. | F29: ✔Perfil comercial con orientación a resultados. ✔Capacidad de negociación y cierre. ✔Autonomía y proactividad. ✔Buen manejo de relaciones interpersonales. ✔Manejo de herramientas digitales. ✔Conocimiento del mercado ganadero (Excluyente) | H29: Buenos Aires - General Pinto | I29: Híbrido | J29: =BASE!J29 -> 46097
A30: =BASE!A30 -> JOB-2025-000029 | B30: =BASE!B30 -> Analista de Mercados | C30: ✔Desarrollar y optimizar herramientas de captura de datos de mercado en tiempo real. ✔Analizar e interpretar información del mercado ganadero para identificar oportunidades de negocio. ✔Diseñar y construir modelos de datos eficientes. ✔Implementar insights y modelos analíticos en estrategias y procesos comerciales. ✔Colaborar con equipos internos para mejorar la toma de decisiones basada en datos. | D30: ✔Estudiantes avanzados de Ing. Industrial, Economía, Administración de Empresas o carreras afines. ✔Interés en el análisis de mercados y modelos de datos. ✔Conocimientos del negocio ganadero (excluyente). ✔Perfil analítico, con capacidad para interpretar información y detectar tendencias. ✔Ganas de aprender y desarrollarse en entornos dinámicos vinculados a tecnología y agronegocios. | E30: ✔Transformar grandes volúmenes de datos del mercado ganadero en información accionable que permita anticipar tendencias y acompañar la toma de decisiones estratégicas del negocio. ✔Desarrollar herramientas de captura y análisis de información en tiempo real, garantizando la calidad y disponibilidad de los datos, y adaptando los modelos analíticos a un mercado dinámico y en constante evolución. ✔Generar insights que contribuyan a optimizar procesos comerciales y detectar nuevas oportunidades de negocio dentro del ecosistema digital de la compañía. | F30: ✔Pensamiento analítico. ✔Capacidad de interpretación de datos. ✔Proactividad. ✔Trabajo en equipo. ✔Orientación a resultados. ✔Curiosidad por el negocio y el mercado. | G30: ✔ Prepaga de primer nivel ✔ Almuerzo en oficina sin costo ✔ Bonificación del 80% en SportClub ✔ Descuentos exclusivos en Samsung ✔ Club de beneficios | H30: =BASE!D30 -> Buenos Aires | I30: Híbrido | J30: =BASE!J30 -> 46097
A31: =BASE!A31 -> JOB-2025-000030 | B31: =BASE!B31 -> Analista de Producto Jr. | C31: ✔Colaborar en la elaboración y mantenimiento de documentación de producto (PRD’s). ✔Relevar procesos internos y participar en el armado de diagramas de flujo. ✔Detectar oportunidades de mejora en funcionalidades y procesos existentes. ✔Definir y dar seguimiento a métricas de éxito de producto. ✔Acompañar el seguimiento de proyectos en desarrollo junto a equipos técnicos. ✔Brindar soporte en la implementación de nuevas funcionalidades o mejoras. ✔Participar en la coordinación entre áreas (Producto, Tecnología, Operaciones, etc.) para asegurar entregables. | D31: ✔Estudiantes de Ingeniería Industrial, Ingeniería en Sistemas o carreras afines. ✔Interés en gestión de producto, mejora de procesos y análisis funcional. ✔Capacidad para comprender procesos de negocio y traducirlos en requerimientos funcionales. ✔Perfil analítico, con orientación a resultados y mejora continua. ✔Buen manejo de herramientas de documentación y seguimiento (ej. Jira, Confluence, Notion o similares). ✔Habilidad para trabajar de manera colaborativa con equipos técnicos y no técnicos. ✔No se requiere experiencia previa, pero se valorará participación en proyectos académicos o laborales vinculados a procesos o producto. | E31: ✔Comprender procesos de negocio complejos vinculados al ecosistema ganadero digital. ✔Traducir necesidades del negocio en requerimientos claros para el equipo de desarrollo. ✔Dar seguimiento a múltiples iniciativas en simultáneo, manteniendo foco en tiempos y calidad de entrega. ✔Asegurar la correcta documentación de funcionalidades y procesos. ✔Acompañar implementaciones garantizando adopción por parte de los usuarios internos. ✔Medir impacto de mejoras implementadas mediante métricas de éxito definidas. | F31: ✔Pensamiento analítico. ✔Organización y gestión del tiempo. ✔Comunicación efectiva. ✔Trabajo en equipo. ✔Orientación a procesos. ✔Proactividad. ✔Capacidad de aprendizaje continuo. ✔Atención al detalle. | G31: ✔ Prepaga de primer nivel ✔ Almuerzo en oficina sin costo ✔ Bonificación del 80% en SportClub ✔ Descuentos exclusivos en Samsung ✔ Club de beneficios | H31: =BASE!D31 -> Buenos Aires | I31: Híbrido | J31: =BASE!J31 -> 46097
A32: =BASE!A32 -> JOB-2025-000031 | B32: =BASE!B32 -> Analista de IA | C32: ✔ Crear e implementar Pruebas de Concepto (PoC) para agentes conversacionales basados en IA. ✔ Diseñar e implementar workflows automatizados utilizando MCPs. ✔ Definir, desarrollar y automatizar flujos de trabajo mediante herramientas como n8n. ✔ Colaborar con áreas de Producto y Procesos en la identificación de oportunidades de automatización. ✔ Realizar seguimiento de implementaciones de soluciones basadas en IA. ✔ Detectar oportunidades de mejora en agentes y procesos automatizados. ✔ Participar en la evaluación automática de desempeño de agentes conversacionales. ✔ Implementar soluciones utilizando técnicas de RAG para optimizar respuestas y performance. ✔ Documentar desarrollos, flujos y configuraciones implementadas. | D32: ✔Estudiantes avanzados o graduados de carreras como Ingeniería en Sistemas, Ingeniería Industrial o afines, con interés en el desarrollo e implementación de soluciones basadas en Inteligencia Artificial. ✔ Conocimiento en herramientas de automatización como n8n. ✔ Uso frecuente de herramientas de IA generativa (ChatGPT, Claude, Cursor, etc.). ✔ Conocimientos en MCPs aplicados a la automatización de procesos. ✔ Familiaridad con arquitecturas RAG. ✔ Interés por el diseño de agentes conversacionales y automatización inteligente. ✔ Capacidad para trabajar de forma colaborativa con equipos técnicos y de negocio. ✔ Perfil analítico, orientado a la mejora continua de procesos mediante tecnología. | E32: ✔ Traducir necesidades de negocio en soluciones automatizadas basadas en IA. ✔ Diseñar agentes conversacionales eficientes en entornos dinámicos. ✔ Asegurar la correcta integración de workflows automatizados en procesos existentes. ✔ Evaluar y optimizar continuamente el rendimiento de agentes implementados. ✔ Adaptarse a nuevas herramientas y tecnologías emergentes en el ecosistema de IA. ✔ Balancear velocidad de implementación con calidad y escalabilidad de las soluciones. ✔ Colaborar en la evolución de prácticas internas vinculadas a IA aplicada a procesos. | F32: ✔ Pensamiento analítico y orientación a la resolución de problemas. ✔ Capacidad de aprendizaje continuo en entornos tecnológicos cambiantes. ✔ Organización y gestión de múltiples implementaciones simultáneas. ✔ Comunicación efectiva con equipos técnicos y no técnicos. ✔ Proactividad en la detección de oportunidades de automatización. ✔ Orientación a resultados y mejora continua. | G32: ✔ Prepaga de primer nivel ✔ Almuerzo en oficina sin costo ✔ Bonificación del 80% en SportClub ✔ Descuentos exclusivos en Samsung ✔ Club de beneficios | H32: =BASE!D32 -> Buenos Aires | I32: Híbrido | J32: =BASE!J32 -> 46097
A33: =BASE!A33 -> JOB-2025-000032 | B33: =BASE!B33 -> React Native | C33: ✔Desarrollar y mantener aplicaciones móviles utilizando React Native ✔Implementar nuevas funcionalidades asegurando calidad y performance ✔Integrar APIs y servicios backend ✔Optimizar la experiencia de usuario y tiempos de respuesta de la aplicación ✔Participar en definiciones técnicas junto al equipo de producto y backend ✔Detectar y corregir bugs garantizando estabilidad de la app ✔Colaborar en procesos de mejora continua y buenas prácticas de desarrollo | D33: ✔Experiencia comprobable desarrollando con React Native ✔Sólidos conocimientos de JavaScript y/o TypeScript ✔Experiencia en integración de APIs REST ✔Conocimiento de control de versiones con Git ✔Experiencia trabajando en entornos ágiles ✔Capacidad para desarrollar interfaces móviles intuitivas y funcionales ✔Perfil proactivo, resolutivo y orientado a resultados | E33: ✔Desarrollar aplicaciones móviles escalables y de alto rendimiento ✔Mejorar continuamente la experiencia del usuario en entornos dinámicos ✔Integrar múltiples servicios externos asegurando estabilidad ✔Acompañar la evolución tecnológica del producto ✔Trabajar en conjunto con backend y producto para lanzar nuevas funcionalidades | F33: ✔Pensamiento lógico y orientación a resolución de problemas ✔Atención al detalle ✔Trabajo en equipo ✔Organización y autonomía ✔Adaptabilidad a cambios ✔Foco en calidad y experiencia de usuario | G33: ✔ Prepaga de primer nivel ✔ Almuerzo en oficina sin costo ✔ Bonificación del 80% en SportClub ✔ Descuentos exclusivos en Samsung ✔ Club de beneficios | H33: =BASE!D33 -> Buenos Aires | I33: Híbrido | J33: =BASE!J33 -> 46097
A34: =BASE!A34 -> JOB-2025-000033 | B34: =BASE!B34 -> Desarrollador Back End - Node. Js | C34: ✔Desarrollar y mantener aplicaciones backend utilizando Node.js ✔Diseñar y desarrollar APIs REST escalables y seguras ✔Integrar servicios externos y bases de datos ✔Optimizar rendimiento y tiempos de respuesta de las aplicaciones ✔Participar en definiciones técnicas junto a producto y otros equipos de desarrollo ✔Implementar buenas prácticas de código y testing ✔Colaborar en procesos de mejora continua y evolución de la arquitectura | D34: ✔Experiencia comprobable desarrollando con Node.js ✔Sólidos conocimientos de JavaScript y/o TypeScript ✔Experiencia en desarrollo y consumo de APIs REST ✔Manejo de bases de datos SQL y/o NoSQL ✔Conocimiento de Git y trabajo colaborativo en repositorios ✔Experiencia en metodologías ágiles ✔Perfil autónomo, resolutivo y orientado a calidad técnica | E34: ✔Desarrollar soluciones backend escalables en un entorno de negocio dinámico ✔Integrar múltiples servicios y sistemas garantizando estabilidad ✔Optimizar performance y arquitectura en aplicaciones de alto tráfico ✔Acompañar la evolución tecnológica del producto ✔Proponer mejoras técnicas que impacten en eficiencia y calidad | F34: ✔Pensamiento analítico ✔Resolución de problemas técnicos complejos ✔Orientación a calidad y detalle ✔Trabajo en equipo ✔Organización y autonomía ✔Adaptabilidad a entornos cambiantes | G34: ✔ Prepaga de primer nivel ✔ Almuerzo en oficina sin costo ✔ Bonificación del 80% en SportClub ✔ Descuentos exclusivos en Samsung ✔ Club de beneficios | H34: =BASE!D34 -> Buenos Aires | I34: Híbrido | J34: =BASE!J34 -> 46097
A35: =BASE!A35 -> JOB-2025-000034 | B35: =BASE!B35 -> PHP Developer | C35: ✔Desarrollar y mantener aplicaciones backend en PHP. ✔Diseñar, desarrollar e integrar APIs REST. ✔Optimizar consultas SQL y performance de bases de datos. ✔Participar en migraciones y mejoras de arquitectura (legacy → frameworks modernos). ✔Colaborar con equipos de producto, análisis y frontend para definir soluciones técnicas. ✔Implementar buenas prácticas de desarrollo, testing y control de versiones. ✔Participar en revisiones de código y mejora continua del software. | D35: ✔Experiencia comprobable en desarrollo PHP (+3 años idealmente). ✔Sólidos conocimientos en MySQL / SQL. ✔Experiencia en desarrollo y consumo de APIs. ✔Conocimientos en frameworks como Laravel (deseable). ✔Experiencia trabajando con metodologías ágiles (Scrum / Kanban). ✔Perfil autónomo, resolutivo y orientado a calidad técnica. ✔Capacidad para trabajar en equipo y buena comunicación con áreas no técnicas. | E35: ✔Trabajar sobre arquitecturas existentes mejorando performance y escalabilidad. ✔Participar en procesos de modernización tecnológica. ✔Desarrollar soluciones robustas en un entorno de negocio dinámico. ✔Integrar múltiples sistemas y APIs externas garantizando estabilidad y seguridad. ✔Aportar mirada técnica para optimizar procesos internos y productos digitales. | F35: ✔Pensamiento lógico y analítico. ✔Orientación a calidad y detalle. ✔Resolución de problemas técnicos complejos. ✔Trabajo colaborativo. ✔Organización y autonomía. ✔Adaptabilidad a entornos cambiantes. | G35: ✔ Prepaga de primer nivel ✔ Almuerzo en oficina sin costo ✔ Bonificación del 80% en SportClub ✔ Descuentos exclusivos en Samsung ✔ Club de beneficios | H35: =BASE!D35 -> Buenos Aires | I35: Híbrido | J35: =BASE!J35 -> 46097
A36: =BASE!A36 -> JOB-2025-000035 | B36: =BASE!B36 -> DevOps | C36: ✔Administrar y mantener servidores Linux. ✔Gestionar tareas de infraestructura, redes y administración de sistemas (sysadmin). ✔Implementar y mantener contenedores utilizando Docker. ✔Colaborar en la gestión y administración de clústeres Kubernetes. ✔Participar en la implementación y mantenimiento de pipelines CI/CD con Jenkins. ✔Automatizar procesos mediante scripting o lenguajes de programación. ✔Colaborar con el equipo de desarrollo para optimizar procesos de despliegue y entornos de trabajo. ✔Participar en el monitoreo y mejora continua de la infraestructura. | D36: ✔Estudiante o graduado de carreras vinculadas a Sistemas, Informática o afines. ✔Perfil Junior con interés en desarrollarse en el área de infraestructura y DevOps. ✔Conocimientos en administración de sistemas Linux. ✔Conocimientos en redes y tareas de sysadmin. ✔Familiaridad con herramientas de contenedores y automatización. ✔Interés por aprender nuevas tecnologías y adaptarse a entornos dinámicos. ✔Buena predisposición para el trabajo en equipo y aprendizaje continuo. | E36: ✔Colaborar en la administración y evolución de la infraestructura tecnológica que soporta las plataformas de la compañía. ✔Acompañar al equipo de desarrollo en la implementación de prácticas DevOps que mejoren los procesos de despliegue y automatización. ✔Contribuir a la estabilidad, escalabilidad y eficiencia de los entornos de desarrollo y producción. ✔Desarrollarse dentro del equipo de tecnología adquiriendo nuevos conocimientos y herramientas de infraestructura y automatización. | F36: ✔Linux (administración de servidores). ✔Redes y administración de sistemas. ✔Docker. ✔Kubernetes. ✔Jenkins. ✔Conocimientos básicos de scripting o programación (Python, Bash u otros). ✔Se valorará conocimiento en herramientas de monitoreo como Signoz o New Relic (no excluyente). | G36: ✔ Prepaga de primer nivel ✔ Almuerzo en oficina sin costo ✔ Bonificación del 80% en SportClub ✔ Descuentos exclusivos en Samsung ✔ Club de beneficios | H36: =BASE!D36 -> Buenos Aires | I36: Híbrido | J36: =BASE!J36 -> 46097
A37: =BASE!A37 -> JOB-2025-000036 | B37: =BASE!B37 -> Paid Media | C37: ✔ Planificar, ejecutar y optimizar campañas de publicidad digital en plataformas como Google Ads y Meta Ads (excluyente). ✔ Gestionar campañas orientadas a generación de leads, tráfico e interacciones, asegurando su correcta implementación y seguimiento. ✔ Monitorear y optimizar el rendimiento de las campañas en función del retorno de inversión (ROAS). ✔ Administrar presupuestos publicitarios garantizando eficiencia en la inversión. ✔ Analizar el comportamiento digital de los usuarios dentro de la app y generar reportes de performance. ✔ Elaborar reportes semanales, mensuales y trimestrales sobre resultados y KPIs. ✔ Gestionar y optimizar banners web y fichas de Google My Business. ✔ Colaborar en la planificación de contenidos junto al equipo de Marketing. ✔ Brindar soporte en eventos institucionales cuando sea requerido. | D37: ✔ Profesional de Marketing, Publicidad, Negocios Digitales o carreras afines. ✔ Experiencia comprobable de al menos 3 años gestionando campañas de Paid Media en Google Ads y Meta Ads. ✔ Sólidos conocimientos en Google Analytics u otras herramientas de medición digital. ✔ Perfil analítico, metódico y orientado al detalle. ✔ Experiencia en control de presupuestos publicitarios y análisis de métricas de performance. ✔ Disponibilidad para participar en eventos de la compañía cuando sea necesario. ✔ Se valorará experiencia adicional en TikTok Ads y LinkedIn Ads. ✔ Disponibilidad para realizar prueba técnica sobre plataformas Google Ads y Meta Ads. | E37: ✔ Maximizar el rendimiento de las campañas digitales asegurando el cumplimiento de los objetivos de adquisición y conversión. ✔ Optimizar continuamente la inversión publicitaria para mejorar el ROAS. ✔ Traducir datos de comportamiento digital en insights accionables para la toma de decisiones. ✔ Adaptar estrategias de campañas a un negocio en crecimiento dentro del ecosistema ganadero digital. ✔ Garantizar consistencia en la medición y análisis de resultados entre múltiples plataformas. ✔ Acompañar la estrategia de posicionamiento digital en eventos y acciones offline. | F37: ✔ Gestión avanzada de campañas en Google Ads y Meta Ads. ✔ Análisis de métricas digitales y performance de campañas. ✔ Orientación a resultados y optimización continua. ✔ Organización y seguimiento de múltiples campañas en simultáneo. ✔ Capacidad de análisis y toma de decisiones basada en datos. ✔ Atención al detalle y planificación estratégica. | G37: ✔ Prepaga de primer nivel ✔ Almuerzo en oficina sin costo ✔ Bonificación del 80% en SportClub ✔ Descuentos exclusivos en Samsung ✔ Club de beneficios | H37: =BASE!D37 -> Buenos Aires | I37: Híbrido | J37: =BASE!J37 -> 46097
A38: =BASE!A38 -> JOB-2025-000037 | B38: =BASE!B38 -> Coordinador de Reclutamiento y Selección de Personal | C38: ✔ Liderar la estrategia de Reclutamiento de forma integral, asegurando la cobertura oportuna de perfiles IT y no IT. ✔ Dar soporte a los líderes de área en la definición de perfiles alineados a las necesidades del negocio. ✔ Gestionar y priorizar un alto volumen de búsquedas, garantizando eficiencia operativa, calidad de ingreso y experiencia del candidato. ✔ Gestionar la contratación y los acuerdos comerciales con las agencias de reclutamiento. ✔ Monitorear y analizar los indicadores clave del área para la toma de decisiones estratégicas y planes de mejora continua. ✔ Liderar la implementación y evolución de herramientas tecnológicas de reclutamiento (ATS, automatizaciones, IA), promoviendo innovación y eficiencia en los procesos. ✔ Gestionar y profesionalizar la base de talento, asegurando trazabilidad, calidad de información y construcción de pipelines estratégicos. ✔ Impulsar estándares de excelencia en los procesos de selección, fortaleciendo la marca empleadora y la experiencia del candidato. | D38: ✔Profesional de de RRHH o carreras afines. ✔Experiencia comprobable de mas de 5 años coordinando procesos de reclutamiento de alto volumen. ✔Experiencia en reclutamiento de perfiles IT (excluyente) y con base de datos propia. ✔Manejo de bases de datos de candidatos y herramientas de gestión. ✔Experiencia o conocimientos en implementación de IA aplicada a procesos de RRHH. ✔Capacidad para trabajar con múltiples procesos en simultáneo. ✔Perfil analítico, organizado y orientado a resultados. | E38: ✔ Alinear el proceso de Reclutamiento a las necesidades actuales de crecimiento sostenido. ✔ Gestionar grandes volúmenes de búsquedas de forma ordenada y eficiente ✔ Automatizar procesos del área para generar información confiable y oportuna para la toma de decisiones ✔ Acompañar a los líderes en la construcción de equipos de alto desempeño y en su propio desarrollo | F38: ✔Gestión y planificación de procesos. ✔Pensamiento analítico orientado a datos. ✔Liderazgo y coordinación. ✔Comunicación efectiva y capacidad de influencia. ✔Proactividad y mejora continua. ✔Adaptabilidad a entornos tecnológicos y digitales. | G38: ✔ Prepaga de primer nivel ✔ Almuerzo en oficina sin costo ✔ Bonificación del 80% en SportClub ✔ Descuentos exclusivos en Samsung ✔ Club de beneficios | H38: =BASE!D38 -> Buenos Aires | I38: Híbrido | J38: =BASE!J38 -> 46097
A39: =BASE!A39 -> JOB-2025-000038 | B39: =BASE!B39 -> Analista de Reclutamiento y Selección de Personal | C39: ✔Realizar procesos de selección de perfiles IT y tradicionales end to end. ✔Realizar screening y entrevistas por competencias. ✔Coordinar entrevistas con líderes internos. ✔Administrar y mantener actualizada la base de datos de candidatos. ✔Gestionar múltiples procesos de selección de forma simultánea. ✔Realizar búsquedas activas en distintas fuentes (bases de datos, portales, LinkedIn). ✔Impulso de iniciativias en el diseño e implementacion de la estrategia de atraccion de taelento. | D39: ✔Estudiante avanzado o graduado/a de Recursos Humanos, Psicología o carreras afines. ✔Experiencia comprobable en procesos de reclutamiento y selección de perfiles IT y tradicional. ✔Experiencia gestionando múltiples procesos de selección en simultáneo en contextos de alto volumen. ✔Manejo de herramientas de reclutamiento (LinkedIn Recruiter, portales de empleo, bases de datos). ✔Experiencia en gestión y mantenimiento de bases de datos de candidatos. ✔Conocimiento en técnicas de búsqueda activa. ✔Perfil organizado, resolutivo y orientado a resultados. ✔Interés en el uso de herramientas tecnológicas aplicadas a procesos de reclutamiento. | E39: ✔Gestionar múltiples procesos de selección en simultáneo, asegurando tiempos de cobertura competitivos sin comprometer la calidad del ingreso. ✔Abordar búsquedas de perfiles IT altamente demandados en un mercado laboral dinámico y competitivo. ✔Construir y mantener pipelines activos de talento que permitan anticiparse a futuras necesidades del negocio. ✔Garantizar la actualización y calidad de la base de datos de candidatos para facilitar procesos de selección ágiles. ✔Adaptar estrategias de búsqueda según el tipo de perfil (IT vs. tradicionales) y seniority requerido. ✔Asegurar una experiencia positiva para el candidato durante todo el proceso de selección. ✔Trabajar en conjunto con el Coordinador del área en la implementación de mejoras en los procesos de reclutamiento basadas en datos. ✔Cumplir con objetivos de cobertura en contextos de alto caudal de búsquedas activas. ✔Utilizar herramientas tecnológicas que optimicen los procesos de sourcing y screening. | F39: ✔Organización y gestión del tiempo. ✔Capacidad de trabajo bajo alto volumen de búsquedas. ✔Búsqueda activa (hunting). ✔Manejo de bases de datos. | G39: ✔ Prepaga de primer nivel ✔ Almuerzo en oficina sin costo ✔ Bonificación del 80% en SportClub ✔ Descuentos exclusivos en Samsung ✔ Club de beneficios | H39: =BASE!D39 -> Buenos Aires | I39: Híbrido | J39: =BASE!J39 -> 46097
A40: =BASE!A40 -> JOB-2025-000039 | B40: =BASE!B40 -> Analista de Atención al Cliente | C40: ✔Gestionar, dar soporte y realizar seguimiento a una cartera de clientes asignada. ✔Atender consultas y brindar soluciones a través de distintos canales de comunicación: WhatsApp, llamados telefónicos, correos electrónicos y mensajería de la plataforma interna. ✔Resolver inquietudes operativas vinculadas al uso de las herramientas de la empresa. ✔Registrar y realizar seguimiento de consultas para garantizar su correcta resolución. ✔Colaborar con otros equipos internos para dar respuesta eficiente a las necesidades de los clientes. ✔Participar en eventos organizados por la empresa. ✔Detectar oportunidades de mejora en los procesos de atención y proponer iniciativas que contribuyan a la automatización y profesionalización del área. ✔Desarrollar conocimiento profundo sobre el funcionamiento y beneficios de las herramientas de DeCampoaCampo. | D40: ✔Estudiantes avanzados o graduados de carreras universitarias, preferentemente vinculadas al agro, administración o áreas afines. ✔Experiencia laboral inicial (0 a 2 años), idealmente en roles de atención al cliente, soporte o contacto con usuarios. ✔Interés por el sector agropecuario y por trabajar en entornos tecnológicos. ✔Disponibilidad para realizar viajes ocasionales al interior del país. | E40: ✔Brindar una experiencia de atención cercana, ágil y resolutiva para los clientes. ✔Comprender en profundidad el funcionamiento de las herramientas tecnológicas de la empresa para poder acompañar a los usuarios. ✔Identificar oportunidades de mejora en los procesos de atención y contribuir activamente a su optimización. ✔Adaptarse a un entorno dinámico con múltiples canales de comunicación y consultas simultáneas. | F40: ✔Orientación al cliente. ✔Capacidad de resolución de problemas. ✔Comunicación clara y asertiva. ✔Empatía y habilidades interpersonales. ✔Proactividad y actitud de mejora continua. ✔Trabajo colaborativo. ✔Capacidad analítica. | G40: ✔ Prepaga de primer nivel ✔ Almuerzo en oficina sin costo ✔ Bonificación del 80% en SportClub ✔ Descuentos exclusivos en Samsung ✔ Club de beneficios | H40: =BASE!D40 -> Buenos Aires | I40: Híbrido | J40: =BASE!J40 -> 46097
A41: =BASE!A41 -> JOB-2025-000040 | B41: =BASE!B41 -> Pasante de Finanzas y Creditos | C41: ✔Control y gestión de formularios crediticios de la empresa. ✔Realizar preaprobaciones de créditos potenciales. ✔Analizar solicitudes de aumento de límites crediticios. ✔Desarrollar y mantener bases de datos vinculadas a información crediticia. ✔Colaborar en la construcción de métricas y reportes relacionados con créditos y límites crediticios. ✔Participar en el análisis de créditos potenciales de productos internos de la empresa. ✔Contribuir al desarrollo y mejora continua de procesos del área financiera. | D41: ✔Estudiantes universitarios en curso (excluyente). ✔Carreras: Administración, Economía, Ingeniería, Finanzas o afines. ✔Interés en análisis financiero, datos y evaluación de riesgo crediticio. ✔Perfil analítico, curioso y con ganas de aprender en un entorno tecnológico. | E41: ✔Desarrollar nuevas métricas y paneles de gestión para el área de créditos. ✔Construir y mantener historial crediticio de empresas. ✔Diseñar procesos para el análisis de situaciones crediticias actuales y potenciales. ✔Identificar riesgos crediticios y generar información que facilite la toma de decisiones financieras. | F41: ✔Capacidad analítica. SQL, Python, Webapps, Agentes de IA ✔Pensamiento lógico y orientación a datos. ✔Proactividad e iniciativa. ✔Capacidad de organización y seguimiento de información. ✔Trabajo colaborativo. | G41: ✔ Prepaga de primer nivel ✔ Almuerzo en oficina sin costo ✔ Bonificación del 80% en SportClub ✔ Descuentos exclusivos en Samsung ✔ Club de beneficios | H41: =BASE!D41 -> Buenos Aires | I41: Híbrido | J41: =BASE!J41 -> 46097
A42: =BASE!A42 -> JOB-2025-000041 | B42: =BASE!B42 | J42: =BASE!J42
A43: =BASE!A43 -> JOB-2025-000042 | B43: =BASE!B43 | J43: =BASE!J43
A44: =BASE!A44 -> JOB-2025-000043 | B44: =BASE!B44 | J44: =BASE!J44
A45: =BASE!A45 -> JOB-2025-000044 | B45: =BASE!B45 | J45: =BASE!J45
A46: =BASE!A46 -> JOB-2025-000045 | B46: =BASE!B46 | J46: =BASE!J46
A47: =BASE!A47 -> JOB-2025-000046 | B47: =BASE!B47 | J47: =BASE!J47
A48: =BASE!A48 -> JOB-2025-000047 | B48: =BASE!B48 | J48: =BASE!J48
A49: =BASE!A49 -> JOB-2025-000048 | B49: =BASE!B49 | J49: =BASE!J49
A50: =BASE!A50 -> JOB-2025-000049 | B50: =BASE!B50 | J50: =BASE!J50
A51: =BASE!A51 -> JOB-2025-000050 | B51: =BASE!B51 | J51: =BASE!J51
A52: =BASE!A52 -> JOB-2025-000051 | B52: =BASE!B52 | J52: =BASE!J52
A53: =BASE!A53 -> JOB-2025-000052 | B53: =BASE!B53 | J53: =BASE!J53
... A387: =BASE!A387 | B387: =BASE!B387 | J387: =BASE!J387
B388: =BASE!B388 | J388: =BASE!J388

Sheet Busquedas ACTIVAS RRHH
A1: Timestamp | B1: ID Posiciones | C1: Posiciones | D1: Nombre Completo | E1: Edad | F1: Provincia | G1: Localidad | H1: Email | I1: Telefono | J1: CV URL
A2: 46124.824 | B2: JOB-2025-000037 | C2: Coordinador de Reclutamiento y Selección de Personal | D2: Rocio iantosca | E2: 33 | F2: Buenos Aires | G2: San isidro | H2: rocioiantosca@gmail.com | I2: 1162030414 | J2: https://drive.google.com/file/d/1xrr6U8wHf4WzE9r39rdLbmTj6gXb7sfy/view?usp=drivesdk
A3: 46124.82 | B3: JOB-2025-000002 | C3: Regional Comercial | D3: Alvaro Di Bin | E3: 27 | F3: Buenos Aires | G3: Pehuajo | H3: alvarodibin@gmail.com | I3: 2396606372 | J3: https://drive.google.com/file/d/1o9I1VrScatlNshqI7ztvGFPldxM_fbht/view?usp=drivesdk
A4: 46124.82 | B4: JOB-2025-000003 | C4: Regional Comercial | D4: Alvaro Di Bin | E4: 27 | F4: Buenos Aires | G4: Pehuajo | H4: alvarodibin@gmail.com | I4: 2396606372 | J4: https://drive.google.com/file/d/1o9I1VrScatlNshqI7ztvGFPldxM_fbht/view?usp=drivesdk
A5: 46124.82 | B5: JOB-2025-000016 | C5: Regional Comercial | D5: Alvaro Di Bin | E5: 27 | F5: Buenos Aires | G5: Pehuajo | H5: alvarodibin@gmail.com | I5: 2396606372 | J5: https://drive.google.com/file/d/1o9I1VrScatlNshqI7ztvGFPldxM_fbht/view?usp=drivesdk
A6: 46122.754 | B6: JOB-2025-000011 | C6: Analista de Operaciones Comerciales | D6: Elias Suarez | E6: 24 | F6: Buenos Aires | G6: CHASCOMUS | H6: eliassuarez033@gmail.com | I6: 2241531237 | J6: https://drive.google.com/file/d/1AlUUIa9mcRmnkduoowqXA1wYLwPOVviU/view?usp=drivesdk
A7: 46122.754 | B7: JOB-2025-000016 | C7: Regional Comercial | D7: Elias Suarez | E7: 24 | F7: Buenos Aires | G7: CHASCOMUS | H7: eliassuarez033@gmail.com | I7: 2241531237 | J7: https://drive.google.com/file/d/1AlUUIa9mcRmnkduoowqXA1wYLwPOVviU/view?usp=drivesdk
A8: 46122.754 | B8: JOB-2025-000024 | C8: Regional Comercial | D8: Elias Suarez | E8: 24 | F8: Buenos Aires | G8: CHASCOMUS | H8: eliassuarez033@gmail.com | I8: 2241531237 | J8: https://drive.google.com/file/d/1AlUUIa9mcRmnkduoowqXA1wYLwPOVviU/view?usp=drivesdk
A9: 46122.754 | B9: JOB-2025-000025 | C9: Regional Comercial | D9: Elias Suarez | E9: 24 | F9: Buenos Aires | G9: CHASCOMUS | H9: eliassuarez033@gmail.com | I9: 2241531237 | J9: https://drive.google.com/file/d/1AlUUIa9mcRmnkduoowqXA1wYLwPOVviU/view?usp=drivesdk
A10: 46122.754 | B10: JOB-2025-000026 | C10: Regional Comercial | D10: Elias Suarez | E10: 24 | F10: Buenos Aires | G10: CHASCOMUS | H10: eliassuarez033@gmail.com | I10: 2241531237 | J10: https://drive.google.com/file/d/1AlUUIa9mcRmnkduoowqXA1wYLwPOVviU/view?usp=drivesdk
A11: 46122.754 | B11: JOB-2025-000027 | C11: Regional Comercial | D11: Elias Suarez | E11: 24 | F11: Buenos Aires | G11: CHASCOMUS | H11: eliassuarez033@gmail.com | I11: 2241531237 | J11: https://drive.google.com/file/d/1AlUUIa9mcRmnkduoowqXA1wYLwPOVviU/view?usp=drivesdk
A12: 46122.754 | B12: JOB-2025-000028 | C12: Regional Comercial | D12: Elias Suarez | E12: 24 | F12: Buenos Aires | G12: CHASCOMUS | H12: eliassuarez033@gmail.com | I12: 2241531237 | J12: https://drive.google.com/file/d/1AlUUIa9mcRmnkduoowqXA1wYLwPOVviU/view?usp=drivesdk
A13: 46122.754 | B13: JOB-2025-000029 | C13: Analista de Mercados | D13: Elias Suarez | E13: 24 | F13: Buenos Aires | G13: CHASCOMUS | H13: eliassuarez033@gmail.com | I13: 2241531237 | J13: https://drive.google.com/file/d/1AlUUIa9mcRmnkduoowqXA1wYLwPOVviU/view?usp=drivesdk
... A34: 46120.443 | B34: JOB-2025-000039 | C34: Analista de Atención al Cliente | D34: Martin Felice | E34: 27 | F34: Buenos Aires | G34: Buenos Aires | H34: felicemartin346@gmail.com | I34: 1160055965 | J34: https://drive.google.com/file/d/1XkhOMd8cP8WlQJ41kRK0bFAYUpW06sj-/view?usp=drivesdk
A35: 46119.796 | B35: JOB-2025-000011 | C35: Analista de Operaciones Comerciales | D35: José Roque Lanús | E35: 22 | F35: Buenos Aires | G35: San Isidro | H35: roquelanus03@gmail.com | I35: +54 (91)1127690831 | J35: https://drive.google.com/file/d/1xte54_7LvrTVsXhWSKSgL7D7VbVMmPAF/view?usp=drivesdk
A36: 46119.666 | B36: JOB-2025-000008 | C36: Analista de Legales | D36: Pedro Jose Lazzaro forastier | E36: 20 | F36: CABA | G36: recoleta | H36: pedrolazzaro1234@gmail.com | I36: 2345454182 | J36: https://drive.google.com/file/d/10uS4aApumhkdmGedYsRzoO2h0CBKtWVb/view?usp=drivesdk
A37: 46119.666 | B37: JOB-2025-000024 | C37: Regional Comercial | D37: Pedro Jose Lazzaro forastier | E37: 20 | F37: CABA | G37: recoleta | H37: pedrolazzaro1234@gmail.com | I37: 2345454182 | J37: https://drive.google.com/file/d/10uS4aApumhkdmGedYsRzoO2h0CBKtWVb/view?usp=drivesdk
A38: 46119.666 | B38: JOB-2025-000040 | C38: Pasante de Finanzas y Creditos | D38: Pedro Jose Lazzaro forastier | E38: 20 | F38: CABA | G38: recoleta | H38: pedrolazzaro1234@gmail.com | I38: 2345454182 | J38: https://drive.google.com/file/d/10uS4aApumhkdmGedYsRzoO2h0CBKtWVb/view?usp=drivesdk
A39: 46119.648 | B39: JOB-2025-000037 | C39: Coordinador de Reclutamiento y Selección de Personal | D39: Guido Luján Ranieri | E39: 35 | F39: Buenos Aires | G39: Pergamino | H39: ranieri_guido@hotmail.com | I39: 2477583353 | J39: https://drive.google.com/file/d/1KKGW1QomQvZh7enDtptFHuwjAAqitJ_a/view?usp=drivesdk
A40: 46119.55 | B40: JOB-2025-000037 | C40: Coordinador de Reclutamiento y Selección de Personal | D40: Lourdes Quinteiros | E40: 40 | F40: Buenos Aires | G40: Santos Lugares | H40: lourdes.quinteiros@gmail.com | I40: 11562767829 | J40: https://drive.google.com/file/d/1O2pOU5_CwUiDlBtfjDGUJOX2Lf7rTcuW/view?usp=drivesdk
A41: 46119.462 | B41: JOB-2025-000011 | C41: Analista de Operaciones Comerciales | D41: Segundo Belletrutti | E41: 23 | F41: Buenos Aires | G41: Capital federal | H41: Segubell2@gmail.com | I41: 2494698544 | J41: https://drive.google.com/file/d/1qZd4MbpouNlx8ycxo28tkswwxNieT4Nj/view?usp=drivesdk
A42: 46119.462 | B42: JOB-2025-000025 | C42: Regional Comercial | D42: Segundo Belletrutti | E42: 23 | F42: Buenos Aires | G42: Capital federal | H42: Segubell2@gmail.com | I42: 2494698544 | J42: https://drive.google.com/file/d/1qZd4MbpouNlx8ycxo28tkswwxNieT4Nj/view?usp=drivesdk
A43: 46119.462 | B43: JOB-2025-000029 | C43: Analista de Mercados | D43: Segundo Belletrutti | E43: 23 | F43: Buenos Aires | G43: Capital federal | H43: Segubell2@gmail.com | I43: 2494698544 | J43: https://drive.google.com/file/d/1qZd4MbpouNlx8ycxo28tkswwxNieT4Nj/view?usp=drivesdk
A44: 46119.432 | B44: JOB-2025-000037 | C44: Coordinador de Reclutamiento y Selección de Personal | D44: Luciana Alejandra Jose | E44: 36 | F44: Buenos Aires | G44: Gerli - Avellaneda | H44: lucianaalejandrajose10@gmail.com | I44: 1133245235 | J44: https://drive.google.com/file/d/1dQcxBhMgNizqvH_Bf1PyN1W78V7f2IOt/view?usp=drivesdk
A45: 46119.428 | B45: JOB-2025-000039 | C45: Analista de Atención al Cliente | D45: Juan Clausen | E45: 25 | F45: CABA | G45: BUENOS AIRES CABA | H45: juanclausen93@gmail.com | I45: (292) 651-7381 | J45: https://drive.google.com/file/d/1IHddZ8YEIBPKgjLmUa3gWzojOcFQsquO/view?usp=drivesdk
A46: 46119.426 | B46: JOB-2025-000011 | C46: Analista de Operaciones Comerciales | D46: Juan Clausen | E46: 25 | F46: CABA | G46: BUENOS AIRES CABA | H46: juanclausen93@gmail.com | I46: (292) 651-7381 | J46: https://drive.google.com/file/d/1BExq-uLkaB9ljNSSuyXWThHfGe8DMJ6d/view?usp=drivesdk
A47: 46119.375 | B47: JOB-2025-000037 | C47: Coordinador de Reclutamiento y Selección de Personal | D47: María Eugenia Ortega | E47: 29 | F47: Buenos Aires | G47: San Antonio de Padua | H47: maaria.eeuge@hotmail.com | I47: 1165888529 | J47: https://drive.google.com/file/d/1av4YNHJ27cFRVqm2oNHYkMMhHySsxNtg/view?usp=drivesdk
A48: 46119.374 | B48: JOB-2025-000038 | C48: Analista de Reclutamiento y Selección de Personal | D48: María Eugenia Ortega | E48: 29 | F48: Buenos Aires | G48: San Antonio de Padua | H48: maaria.eeuge@hotmail.com | I48: 1165888529 | J48: https://drive.google.com/file/d/1Sw4aowBM7TEewgXdegKTbxm7qMVVIo7n/view?usp=drivesdk
A49: 46118.974 | B49: JOB-2025-000037 | C49: Coordinador de Reclutamiento y Selección de Personal | D49: jessika Bottini | E49: 40 | F49: Buenos Aires | G49: BUENOS AIRES | H49: jessikabottinirrhh@gmail.com | I49: 111533516289 | J49: https://drive.google.com/file/d/1CKviSz0xxss_Ogk-V9k3u8Sm5Qz8vkfy/view?usp=drivesdk
A50: 46118.913 | B50: JOB-2025-000038 | C50: Analista de Reclutamiento y Selección de Personal | D50: Rosxy Romero | E50: 33 | F50: CABA | G50: Caballito | H50: rosxybell@gmail.com | I50: 1126729118 | J50: https://drive.google.com/file/d/13R6QSKFELk_IpFHrvy1GphX_fU8J9Cmt/view?usp=drivesdk
A51: 46118.739 | B51: JOB-2025-000037 | C51: Coordinador de Reclutamiento y Selección de Personal | D51: agustin vidal | E51: 31 | F51: Buenos Aires | G51: caba | H51: agustin.vp94@gmail.com | I51: 1158825179 | J51: https://drive.google.com/file/d/1rvpQUv9BvMoIJfoHiPdUGhxhwceklMUP/view?usp=drivesdk
A52: 46118.739 | B52: JOB-2025-000038 | C52: Analista de Reclutamiento y Selección de Personal | D52: agustin vidal | E52: 31 | F52: Buenos Aires | G52: caba | H52: agustin.vp94@gmail.com | I52: 1158825179 | J52: https://drive.google.com/file/d/1rvpQUv9BvMoIJfoHiPdUGhxhwceklMUP/view?usp=drivesdk
A53: 46118.739 | B53: JOB-2025-000039 | C53: Analista de Atención al Cliente | D53: agustin vidal | E53: 31 | F53: Buenos Aires | G53: caba | H53: agustin.vp94@gmail.com | I53: 1158825179 | J53: https://drive.google.com/file/d/1rvpQUv9BvMoIJfoHiPdUGhxhwceklMUP/view?usp=drivesdk
A54: 46118.666 | B54: JOB-2025-000040 | C54: Pasante de Finanzas y Creditos | D54: Lucia Gaggioli | E54: 23 | F54: Buenos Aires | G54: Hurlingham | H54: lucia.gaggioli@gmail.com | I54: 1125177006 | J54: https://drive.google.com/file/d/18JFc1qe3lx-7xcYwDyP5n9Y_XZNPqwuS/view?usp=drivesdk
A55: 46118.666 | B55: JOB-2025-000039 | C55: Analista de Atención al Cliente | D55: Lucia Gaggioli | E55: 23 | F55: Buenos Aires | G55: Hurlingham | H55: lucia.gaggioli@gmail.com | I55: 1125177006 | J55: https://drive.google.com/file/d/18JFc1qe3lx-7xcYwDyP5n9Y_XZNPqwuS/view?usp=drivesdk
A56: 46118.664 | B56: JOB-2025-000030 | C56: Analista de Producto Jr. | D56: Alejo Aliberti | E56: 27 | F56: Buenos Aires | G56: longchamps | H56: alibertialejo56@gmail.com | I56: 1162035637 | J56: https://drive.google.com/file/d/16q-OymWe9LSsajsu9JT8intwDEFf7VhI/view?usp=drivesdk
A57: 46118.664 | B57: JOB-2025-000037 | C57: Coordinador de Reclutamiento y Selección de Personal | D57: Mariana Ricciardi | E57: 38 | F57: Buenos Aires | G57: Aldo bonzi | H57: mariana.c.ricciardi@gmail.com | I57: 1136738952 | J57: https://drive.google.com/file/d/1v6iBvL1FNw5O3anA5HWkMEuhZBFAGtSl/view?usp=drivesdk
A58: 46118.659 | B58: JOB-2025-000038 | C58: Analista de Reclutamiento y Selección de Personal | D58: Marianela Belen Cassese | E58: 31 | F58: Buenos Aires | G58: Ramos Mejia | H58: marianelacassese@gmail.com | I58: 1140721358 | J58: https://drive.google.com/file/d/1fYNpdNKwlZ9Cakq6pZeLBz91qOHlKV6w/view?usp=drivesdk
A59: 46118.617 | B59: JOB-2025-000038 | C59: Analista de Reclutamiento y Selección de Personal | D59: Magali Arias | E59: 25 | F59: CABA | G59: Capital Federal | H59: magaliarias2@gmail.com | I59: 2983608491 | J59: https://drive.google.com/file/d/1NGGdkIcvCx8AaNoAkngbAesFAmvnmx4a/view?usp=drivesdk
A60: 46118.615 | B60: JOB-2025-000037 | C60: Coordinador de Reclutamiento y Selección de Personal | D60: Noelia Garabato | E60: 37 | F60: Buenos Aires | G60: ezeiza | H60: noeliagarabato@gmail.com | I60: 011 7601-9588 | J60: https://drive.google.com/file/d/17--eOokv1zUL_jXK2l_MGmhVzhGCSSIs/view?usp=drivesdk
A61: 46118.599 | B61: JOB-2025-000037 | C61: Coordinador de Reclutamiento y Selección de Personal | D61: Alan Emir Suarez | E61: 36 | F61: CABA | G61: Nuñez | H61: alansuarez@live.com | I61: 1168852466 | J61: https://drive.google.com/file/d/1bfsj9rVsGDKaT6tvLJLZGBGwV6fxtdzJ/view?usp=drivesdk
A62: 46118.55 | B62: JOB-2025-000038 | C62: Analista de Reclutamiento y Selección de Personal | D62: Alexandra Pacheco | E62: 38 | F62: CABA | G62: CABA | H62: anathaly98@gmail.com | I62: 1132742001 | J62: https://drive.google.com/file/d/1rgf4dNf3G8VoyzBb9DJuNA_iH12lSOGB/view?usp=drivesdk
A63: 46118.542 | B63: JOB-2025-000037 | C63: Coordinador de Reclutamiento y Selección de Personal | D63: Alexandra Pacheco | E63: 38 | F63: CABA | G63: CABA | H63: anathaly98@gmail.com | I63: 1132742001 | J63: https://drive.google.com/file/d/13MDsRNYYcPqIxCQQRV_vCm7-ZhamM199/view?usp=drivesdk
A64: 46118.528 | B64: JOB-2025-000037 | C64: Coordinador de Reclutamiento y Selección de Personal | D64: Iara Paiz | E64: 27 | F64: CABA | G64: Caba | H64: iaramicolpaiz@gmail.com | I64: 1136707315 | J64: https://drive.google.com/file/d/1WL0htGCM_wHXFkI1yEKz4l0dIE8ZzPHU/view?usp=drivesdk
A65: 46118.494 | B65: JOB-2025-000037 | C65: Coordinador de Reclutamiento y Selección de Personal | D65: Claudio Mendoza Bernal | E65: 48 | F65: Buenos Aires | G65: Monserrat | H65: cmconsultoria.rrhh@gmail.com | I65: 1154212884 | J65: https://drive.google.com/file/d/1jfYL8xe4NXyIGy7Hxrqp3-b8iBgkFwUx/view?usp=drivesdk
A66: 46118.484 | B66: JOB-2025-000038 | C66: Analista de Reclutamiento y Selección de Personal | D66: María Agustina Lucas | E66: 29 | F66: Buenos Aires | G66: Banfield | H66: mariaagustinalucas@gmail.com | I66: 1158211973 | J66: https://drive.google.com/file/d/1hzwxP6yzpsUtvWq0ADDQCHJhQDiW-gPO/view?usp=drivesdk
A67: 46118.483 | B67: JOB-2025-000037 | C67: Coordinador de Reclutamiento y Selección de Personal | D67: María Agustina Lucas | E67: 29 | F67: Buenos Aires | G67: Banfield | H67: mariaagustinalucas@gmail.com | I67: 1158211973 | J67: https://drive.google.com/file/d/17VUqAGChQS4IQZHUgWTJD6ib_Ykz1Y9J/view?usp=drivesdk
A68: 46118.48 | B68: JOB-2025-000037 | C68: Coordinador de Reclutamiento y Selección de Personal | D68: ALEXIS AGUDELO DUQUE | E68: 32 | F68: CABA | G68: Chacarita | H68: alexis.agudelop@gmail.com | I68: 93884560200 | J68: https://drive.google.com/file/d/1hL0zvOEpgmgF5158D1MyN5iv-JY29MWA/view?usp=drivesdk
A69: 46118.474 | B69: JOB-2025-000038 | C69: Analista de Reclutamiento y Selección de Personal | D69: Giuliana | E69: 35 | F69: CABA | G69: Paternal | H69: giulianacarroll@outlook.com | I69: 1151381638 | J69: https://drive.google.com/file/d/1OFCI7HrcJwpTnEzh4xtKKxjKdh8NXj0a/view?usp=drivesdk
A70: 46118.473 | B70: JOB-2025-000037 | C70: Coordinador de Reclutamiento y Selección de Personal | D70: Giuliana Carroll | E70: 35 | F70: CABA | G70: Paternal | H70: giulianacarroll@outlook.com | I70: 1151381638 | J70: https://drive.google.com/file/d/1vv8pg0xlbJFsfZOV1rYqap2Hpl3mdeFY/view?usp=drivesdk
A71: 46118.463 | B71: JOB-2025-000037 | C71: Coordinador de Reclutamiento y Selección de Personal | D71: Laura Siccardi | E71: 38 | F71: Buenos Aires | G71: Malvinas Argentinas | H71: lsiccardi01@gmail.com | I71: 1157567697 | J71: https://drive.google.com/file/d/1x3rli79v3OOPnotTkd8aBUJnKYvxuX0Z/view?usp=drivesdk
A72: 46118.454 | B72: JOB-2025-000037 | C72: Coordinador de Reclutamiento y Selección de Personal | D72: Patricio Oscar Areco | E72: 35 | F72: CABA | G72: Barracas | H72: patricio.areco22@gmail.com | I72: +5491134915337 | J72: https://drive.google.com/file/d/1l4uiSzWngysiSNdTq_NxFiVDEm55XOXJ/view?usp=drivesdk
A73: 46118.448 | B73: JOB-2025-000040 | C73: Pasante de Finanzas y Creditos | D73: Tomas Montes de Oca | E73: 24 | F73: CABA | G73: CABA | H73: tomymdo01@gmail.com | I73: 1136843448 | J73: https://drive.google.com/file/d/1-mU1p8JCE_cznfHclIc7OFGJmLrMMzIX/view?usp=drivesdk
A74: 46118.393 | B74: JOB-2025-000037 | C74: Coordinador de Reclutamiento y Selección de Personal | D74: Gabriela Gisele Garcia | E74: 36 | F74: CABA | G74: CABA, Flores | H74: garciagabrielagisele8@gmail.com | I74: 1144444158 | J74: https://drive.google.com/file/d/1i1OUxwdLkiBm1ZvMKw2KlkPdlbWFDXQr/view?usp=drivesdk
A75: 46118.389 | B75: JOB-2025-000037 | C75: Coordinador de Reclutamiento y Selección de Personal | D75: Laura Beatriz Gonzalez | E75: 52 | F75: CABA | G75: Almagro | H75: laugonargentina@hotmail.com | I75: 1137565089 | J75: https://docs.google.com/document/d/1T5gWIbivTNgS-1f9OLgnTeAdSdrtQr7T/edit?usp=drivesdk&ouid=112309154375522605745&rtpof=true&sd=true
A76: 46118.378 | B76: JOB-2025-000040 | C76: Pasante de Finanzas y Creditos | D76: Gonzalo Beraza | E76: 24 | F76: CABA | G76: CABA | H76: gonzaloberaza@gmail.com | I76: 2262 303463 | J76: https://drive.google.com/file/d/1M4SkL55cZgH-Ih2RVniIzvhfGwmg7e16/view?usp=drivesdk
A77: 46118.378 | B77: JOB-2025-000036 | C77: Paid Media | D77: Gonzalo Beraza | E77: 24 | F77: CABA | G77: CABA | H77: gonzaloberaza@gmail.com | I77: 2262 303463 | J77: https://drive.google.com/file/d/1M4SkL55cZgH-Ih2RVniIzvhfGwmg7e16/view?usp=drivesdk
A78: 46118.378 | B78: JOB-2025-000030 | C78: Analista de Producto Jr. | D78: Gonzalo Beraza | E78: 24 | F78: CABA | G78: CABA | H78: gonzaloberaza@gmail.com | I78: 2262 303463 | J78: https://drive.google.com/file/d/1M4SkL55cZgH-Ih2RVniIzvhfGwmg7e16/view?usp=drivesdk
A79: 46118.378 | B79: JOB-2025-000011 | C79: Analista de Operaciones Comerciales | D79: Gonzalo Beraza | E79: 24 | F79: CABA | G79: CABA | H79: gonzaloberaza@gmail.com | I79: 2262 303463 | J79: https://drive.google.com/file/d/1M4SkL55cZgH-Ih2RVniIzvhfGwmg7e16/view?usp=drivesdk
A80: 46118.378 | B80: JOB-2025-000029 | C80: Analista de Mercados | D80: Gonzalo Beraza | E80: 24 | F80: CABA | G80: CABA | H80: gonzaloberaza@gmail.com | I80: 2262 303463 | J80: https://drive.google.com/file/d/1M4SkL55cZgH-Ih2RVniIzvhfGwmg7e16/view?usp=drivesdk
A81: 46118.365 | B81: JOB-2025-000037 | C81: Coordinador de Reclutamiento y Selección de Personal | D81: Mercedes Casela | E81: 43 | F81: CABA | G81: Belgrano | H81: mercasela@gmail.com | I81: 1121742866 | J81: https://drive.google.com/file/d/1eFyN8b4gx8sn2k9zdKxCEclW5xrri76C/view?usp=drivesdk
A82: 46118.365 | B82: JOB-2025-000038 | C82: Analista de Reclutamiento y Selección de Personal | D82: Melisa Palomino | E82: 31 | F82: Buenos Aires | G82: Avellaneda | H82: medicpalo@gmail.com | I82: 1169379715 | J82: https://drive.google.com/file/d/1Jbsdve3xC4W96zCQzgGuh2pYJ6jJ8X1P/view?usp=drivesdk
A83: 46118.3 | B83: JOB-2025-000037 | C83: Coordinador de Reclutamiento y Selección de Personal | D83: Sofia Del Prete | E83: 25 | F83: Buenos Aires | G83: Martín Coronado | H83: sdelprete00@outlook.com | I83: 1125175784 | J83: https://drive.google.com/file/d/1Cp5vRVQNs7XkWd_ivtUeITA0NhrivINr/view?usp=drivesdk
A84: 46117.918 | B84: JOB-2025-000038 | C84: Analista de Reclutamiento y Selección de Personal | D84: Sol Lezica | E84: 26 | F84: Buenos Aires | G84: La plata | H84: sollezica257@gmail.com | I84: 2914020111 | J84: https://drive.google.com/file/d/1zKnbzUMh_YCYDhD2Ab4Xxl58ScK3OpCC/view?usp=drivesdk
A85: 46117.82 | B85: JOB-2025-000037 | C85: Coordinador de Reclutamiento y Selección de Personal | D85: Natalia Di Domenico | E85: 41 | F85: Mendoza | G85: Godoy Cruz | H85: natisdidomenico@gmail.com | I85: +542617097223 | J85: https://drive.google.com/file/d/1guz-oecl6NlpdnLtLNvVI7jFIb9Xw8Iz/view?usp=drivesdk
A86: 46117.82 | B86: JOB-2025-000038 | C86: Analista de Reclutamiento y Selección de Personal | D86: Natalia Di Domenico | E86: 41 | F86: Mendoza | G86: Godoy Cruz | H86: natisdidomenico@gmail.com | I86: +542617097223 | J86: https://drive.google.com/file/d/1guz-oecl6NlpdnLtLNvVI7jFIb9Xw8Iz/view?usp=drivesdk
A87: 46117.816 | B87: JOB-2025-000037 | C87: Coordinador de Reclutamiento y Selección de Personal | D87: Romina López | E87: 35 | F87: Buenos Aires | G87: Ezeiza | H87: lopezromina.at@hotmail.com | I87: 1133575122 | J87: https://drive.google.com/file/d/1bm1L1wWJDsAnMS6WFkxaHXbuKEBvlWb_/view?usp=drivesdk
A88: 46117.763 | B88: JOB-2025-000037 | C88: Coordinador de Reclutamiento y Selección de Personal | D88: Florencia | E88: 27 | F88: CABA | G88: Recoleta | H88: lic.guerinflorencia@gmail.com | I88: 1134018579 | J88: https://drive.google.com/file/d/1PZjegKCrjyabhNNBlsC0BwZDppw1ZBlO/view?usp=drivesdk
A89: 46117.558 | B89: JOB-2025-000037 | C89: Coordinador de Reclutamiento y Selección de Personal | D89: Maria Cecilia Conti | E89: 48 | F89: Santa Cruz | G89: El Calafate | H89: macecicon9@gmail.com | I89: 1166696328 | J89: https://drive.google.com/file/d/1WsnpJxRi5WA4almFQLeRvFTQGQNEu3Ml/view?usp=drivesdk
A90: 46117.398 | B90: JOB-2025-000011 | C90: Analista de Operaciones Comerciales | D90: Bautista Pai | E90: 23 | F90: CABA | G90: Caballito | H90: bautistapai@gmail.com | I90: 1136776909 | J90: https://drive.google.com/file/d/1QE1BGHCsUUyZoL7_WgFSjvmL-h2pMBLn/view?usp=drivesdk
A91: 46117.398 | B91: JOB-2025-000029 | C91: Analista de Mercados | D91: Bautista Pai | E91: 23 | F91: CABA | G91: Caballito | H91: bautistapai@gmail.com | I91: 1136776909 | J91: https://drive.google.com/file/d/1QE1BGHCsUUyZoL7_WgFSjvmL-h2pMBLn/view?usp=drivesdk
A92: 46117.398 | B92: JOB-2025-000039 | C92: Analista de Atención al Cliente | D92: Bautista Pai | E92: 23 | F92: CABA | G92: Caballito | H92: bautistapai@gmail.com | I92: 1136776909 | J92: https://drive.google.com/file/d/1QE1BGHCsUUyZoL7_WgFSjvmL-h2pMBLn/view?usp=drivesdk
A93: 46117.106 | B93: JOB-2025-000016 | C93: Regional Comercial | D93: Juan Bautista Canavese | E93: 30 | F93: Buenos Aires | G93: Buenos Aires | H93: canavese_11@hotmail.com | I93: 1136298924 | J93: https://drive.google.com/file/d/1kh5NwszGbjM3vuoTKHU8B-xzKWm4DSKd/view?usp=drivesdk
A94: 46117.106 | B94: JOB-2025-000024 | C94: Regional Comercial | D94: Juan Bautista Canavese | E94: 30 | F94: Buenos Aires | G94: Buenos Aires | H94: canavese_11@hotmail.com | I94: 1136298924 | J94: https://drive.google.com/file/d/1kh5NwszGbjM3vuoTKHU8B-xzKWm4DSKd/view?usp=drivesdk
A95: 46117.106 | B95: JOB-2025-000010 | C95: Gerente de Unidad Financiera | D95: Juan Bautista Canavese | E95: 30 | F95: Buenos Aires | G95: Buenos Aires | H95: canavese_11@hotmail.com | I95: 1136298924 | J95: https://drive.google.com/file/d/1kh5NwszGbjM3vuoTKHU8B-xzKWm4DSKd/view?usp=drivesdk
A96: 46117.106 | B96: JOB-2025-000030 | C96: Analista de Producto Jr. | D96: Juan Bautista Canavese | E96: 30 | F96: Buenos Aires | G96: Buenos Aires | H96: canavese_11@hotmail.com | I96: 1136298924 | J96: https://drive.google.com/file/d/1kh5NwszGbjM3vuoTKHU8B-xzKWm4DSKd/view?usp=drivesdk
A97: 46117.106 | B97: JOB-2025-000011 | C97: Analista de Operaciones Comerciales | D97: Juan Bautista Canavese | E97: 30 | F97: Buenos Aires | G97: Buenos Aires | H97: canavese_11@hotmail.com | I97: 1136298924 | J97: https://drive.google.com/file/d/1kh5NwszGbjM3vuoTKHU8B-xzKWm4DSKd/view?usp=drivesdk
A98: 46117.106 | B98: JOB-2025-000029 | C98: Analista de Mercados | D98: Juan Bautista Canavese | E98: 30 | F98: Buenos Aires | G98: Buenos Aires | H98: canavese_11@hotmail.com | I98: 1136298924 | J98: https://drive.google.com/file/d/1kh5NwszGbjM3vuoTKHU8B-xzKWm4DSKd/view?usp=drivesdk
... A125: 46114.764 | B125: JOB-2025-000037 | C125: Coordinador de Reclutamiento y Selección de Personal | D125: Cynthia Elizabeth Tolaba | E125: 31 | F125: Buenos Aires | G125: Lomas de Zamora, GBA Sur, Argentina | H125: cynthiatolaba09@gmail.com | I125: 1133300127 | J125: https://drive.google.com/file/d/1LSVBdSr_q5OH53XXK0A3E2TBongxdx1g/view?usp=drivesdk
A126: 46114.721 | B126: JOB-2025-000037 | C126: Coordinador de Reclutamiento y Selección de Personal | D126: Gabriel Blanch López | E126: 27 | F126: Mendoza | G126: Mendoza | H126: gabrielblanchlopez@gmail.com | I126: 2613672439
A127: 46114.721 | B127: JOB-2025-000038 | C127: Analista de Reclutamiento y Selección de Personal | D127: Gabriel Blanch López | E127: 27 | F127: Mendoza | G127: Mendoza | H127: gabrielblanchlopez@gmail.com | I127: 2613672439 | J127: https://drive.google.com/file/d/1LSVBdSr_q5OH53XXK0A3E2TBongxdx1g/view?usp=drivesdk
A128: 46114.718 | B128: JOB-2025-000037 | C128: Coordinador de Reclutamiento y Selección de Personal | D128: María de los Ángeles Delaloyeq | E128: 41 | F128: CABA | G128: CABA | H128: maria.delaloye@gmail.com | I128: 1134112783 | J128: https://drive.google.com/file/d/1unaVOYAxQwFyfe_AOHfHkRTsrXcpiaPV/view?usp=drivesdk
A129: 46114.671 | B129: JOB-2025-000038 | C129: Analista de Reclutamiento y Selección de Personal | D129: Melina Gimenez | E129: 28 | F129: Buenos Aires | G129: Boedo | H129: meliyael.gimenez@gmail.com | I129: 1136345696 | J129: https://drive.google.com/file/d/1mVS774GUvDvjQM4vBgVv1mdnXoaEyxdr/view?usp=drivesdk
A130: 46114.577 | B130: JOB-2025-000037 | C130: Coordinador de Reclutamiento y Selección de Personal | D130: Gisela Karina Saia | E130: 58 | F130: Buenos Aires | G130: Pilae | H130: saiagisel@gmail.com | I130: 1126651710 | J130: https://drive.google.com/file/d/1ZsfIVMcWY8W1PSZMTBFJmnPHSh2OOe3C/view?usp=drivesdk
A131: 46114.523 | B131: JOB-2025-000037 | C131: Coordinador de Reclutamiento y Selección de Personal | D131: Jessica Tecaziner | E131: 34 | F131: CABA | G131: Villa Pueyrredón | H131: jessitecaziner@gmail.com | I131: 1159952424 | J131: https://drive.google.com/file/d/1OfB6NPLPNjnwBBYi_meJgK6-h_vnQ5_D/view?usp=drivesdk
A132: 46114.522 | B132: JOB-2025-000039 | C132: Analista de Atención al Cliente | D132: Brenda Carla Bianchi | E132: 30 | F132: CABA | G132: Caballito | H132: bianchi.brenda.carla@gmail.com | I132: 1138000045 | J132: https://drive.google.com/file/d/19Qiy-us24ULRZ4tSip4Mg1l6DlRrbU2l/view?usp=drivesdk
A133: 46114.496 | B133: JOB-2025-000037 | C133: Coordinador de Reclutamiento y Selección de Personal | D133: Florencia Daraio | E133: 32 | F133: CABA | G133: CABA, Palermo | H133: lic.daraio@gmail.com | I133: 1133127865 | J133: https://drive.google.com/file/d/19UnMCcwlioeblzQLauA9v09ow6q2hu27/view?usp=drivesdk
A134: 46114.488 | B134: JOB-2025-000038 | C134: Analista de Reclutamiento y Selección de Personal | D134: Paula Calandrelli | E134: 40 | F134: CABA | G134: CABA | H134: paula_calandrelli@hotmail.com | I134: 1144081109 | J134: https://drive.google.com/file/d/1bIcpTZPmsoGZuO9ATHGYufGk1CGIQbM4/view?usp=drivesdk
A135: 46114.484 | B135: JOB-2025-000037 | C135: Coordinador de Reclutamiento y Selección de Personal | D135: Karen Jara | E135: 48 | F135: CABA | G135: CABA | H135: jarakaren.hr@gmail.com | I135: 1163781638 | J135: https://drive.google.com/file/d/18MVwol4ACev8hLCVMgFaIcUU_-AMLBkI/view?usp=drivesdk
A136: 46114.461 | B136: JOB-2025-000039 | C136: Analista de Atención al Cliente | D136: Sofía Buchanan | E136: 27 | F136: Buenos Aires | G136: Pilar | H136: sofiabuchananvivot@gmail.com | I136: 1159044956 | J136: https://drive.google.com/file/d/1GVCP5F9R8S1tXNCgOMj7M8R5BPdba2rt/view?usp=drivesdk
A137: 46114.458 | B137: JOB-2025-000011 | C137: Analista de Operaciones Comerciales | D137: Sofía | E137: 27 | F137: Buenos Aires | G137: pilar | H137: sofiabuchananvivot@gmail.com | I137: 1159044956 | J137: https://drive.google.com/file/d/11rBldzlHpZoXnKHGtzQcLvKu6i4nRLqF/view?usp=drivesdk
A138: 46114.442 | B138: JOB-2025-000039 | C138: Analista de Atención al Cliente | D138: Mayra Alejandra Ojeda Paredes | E138: 29 | F138: CABA | G138: Parque Patricios | H138: ojedamayra65@gmail.com | I138: 1122938759 | J138: https://drive.google.com/file/d/1DVGVlVQf4LQa1zWwswdp8l24MtjiIEFI/view?usp=drivesdk
... A160: 46113.805 | B160: JOB-2025-000037 | C160: Coordinador de Reclutamiento y Selección de Personal | D160: Ingrid Lorena Vadalá | E160: 46 | F160: CABA | G160: Caballito | H160: i_vadala@hotmail.com | I160: 1152267828 | J160: https://drive.google.com/file/d/1tm8h0Z64E4fZUiKWvMtygv1UXwZ57nzF/view?usp=drivesdk
A161: 46113.798 | B161: JOB-2025-000036 | C161: Paid Media | D161: Julieta Natalia Carducci | E161: 21 | F161: Buenos Aires | G161: Vicente Lopez | H161: julietacarducci10@gmail.com | I161: 11 2455 - 6808 | J161: https://drive.google.com/file/d/18-_nlA_tlUt09DHgyNnxVmaODtCCDnBN/view?usp=drivesdk
A162: 46113.783 | B162: JOB-2025-000037 | C162: Coordinador de Reclutamiento y Selección de Personal | D162: Lorena cano | E162: 43 | F162: CABA | G162: Capital federal | H162: Lorenacanno82@gmail.com | I162: 1165375506 | J162: https://drive.google.com/file/d/1DXPN0WbAgYv1cniN8XC85A60wwSEo_xd/view?usp=drivesdk
A163: 46113.781 | B163: JOB-2025-000037 | C163: Coordinador de Reclutamiento y Selección de Personal | D163: Daniela Belen Garcia | E163: 39 | F163: CABA | G163: Caba | H163: daniela.b.garcia02@gmail.com | I163: 1134800089 | J163: https://drive.google.com/file/d/1VQEjURstLANCn90aZY89yJUy_rAmXQKh/view?usp=drivesdk
A164: 46113.773 | B164: JOB-2025-000037 | C164: Coordinador de Reclutamiento y Selección de Personal | D164: Gonzalo Fabián Taretto | E164: 33 | F164: CABA | G164: Chacarita | H164: g.taretto92@gmail.com | I164: 111562673792 | J164: https://drive.google.com/file/d/11PziVWpiShqoqdLKyojCMqihnFuvR2MP/view?usp=drivesdk
A165: 46113.768 | B165: JOB-2025-000038 | C165: Analista de Reclutamiento y Selección de Personal | D165: Valeria Rodriguez Alvarez | E165: 52 | F165: Buenos Aires | G165: Lanús | H165: rodriguezvaleriac@gmail.com | I165: 1136917928 | J165: https://drive.google.com/file/d/1pakOSMDwTzwYgJGJF4NTCbzY0iwHRT0F/view?usp=drivesdk
A166: 46113.767 | B166: JOB-2025-000038 | C166: Analista de Reclutamiento y Selección de Personal | D166: Nicolas Ruben Villalba | E166: 38 | F166: Buenos Aires | G166: Ciudadela | H166: nicolasvillalba88@gmail.com | I166: 1162823610 | J166: https://drive.google.com/file/d/1srZJIOYrMCe2EJf2GHP7bxL8K6kYuuF6/view?usp=drivesdk
A167: 46113.762 | B167: JOB-2025-000038 | C167: Analista de Reclutamiento y Selección de Personal | D167: Ticiana Pacin Pacin | E167: 44 | F167: Buenos Aires | G167: Avellaneda | H167: ticiana.pacin@hotmail.com | I167: 1153790471 | J167: https://drive.google.com/file/d/1ocMHpuKKj6FwhoWZJgKB9SjBdchc5Xdu/view?usp=drivesdk
...

Sheet VISITS
A1: timestamp | B1: event_name | C1: job_id | D1: page | E1: utm_source | F1: utm_medium | G1: utm_campaign | H1: utm_content | I1: utm_term | J1: referrer | K1: user_agent | L1: device | M1: visitor_id | N1: is_returning
A2: 46116.825 | B2: page_view | D2: /userCodeAppPanel | J2: https://n-h2l2qss2sclrg4n74cjzkbuuq76zyb6l2fgpgeq-0lu-script.googleusercontent.com/ | K2: Mozilla/5.0 (Linux; Android 10; K) AppleWebKit/537.36 (KHTML, like Gecko) SamsungBrowser/29.0 Chrome/136.0.0.0 Mobile Safari/537.36 | L2: mobile | M2: dc01200e-bb5a-44df-82f3-f06a080ae4d0 | N2: SI
A3: 46116.806 | B3: view_job | C3: JOB-2025-000039 | D3: /portal-busquedas/ | J3: https://www.linkedin.com/ | K3: Mozilla/5.0 (iPhone; CPU iPhone OS 18_7 like Mac OS X) AppleWebKit/605.1.15 (KHTML, like Gecko) Version/26.3 Mobile/15E148 Safari/604.1 | L3: mobile | M3: 329f3f0d-df3f-4745-8c8c-9d423832d55c | N3: NO
A4: 46116.806 | B4: view_job | C4: JOB-2025-000039 | D4: /portal-busquedas/ | J4: https://www.linkedin.com/ | K4: Mozilla/5.0 (iPhone; CPU iPhone OS 18_7 like Mac OS X) AppleWebKit/605.1.15 (KHTML, like Gecko) Version/26.3 Mobile/15E148 Safari/604.1 | L4: mobile | M4: 329f3f0d-df3f-4745-8c8c-9d423832d55c | N4: NO
A5: 46116.799 | B5: view_job | C5: JOB-2025-000039 | D5: /portal-busquedas/ | J5: https://www.linkedin.com/ | K5: Mozilla/5.0 (iPhone; CPU iPhone OS 18_7 like Mac OS X) AppleWebKit/605.1.15 (KHTML, like Gecko) Version/26.3 Mobile/15E148 Safari/604.1 | L5: mobile | M5: 329f3f0d-df3f-4745-8c8c-9d423832d55c | N5: NO
A6: 46116.799 | B6: view_job | C6: JOB-2025-000039 | D6: /portal-busquedas/ | J6: https://www.linkedin.com/ | K6: Mozilla/5.0 (iPhone; CPU iPhone OS 18_7 like Mac OS X) AppleWebKit/605.1.15 (KHTML, like Gecko) Version/26.3 Mobile/15E148 Safari/604.1 | L6: mobile | M6: 329f3f0d-df3f-4745-8c8c-9d423832d55c | N6: NO
A7: 46116.799 | B7: page_view | D7: /portal-busquedas/ | J7: https://www.linkedin.com/ | K7: Mozilla/5.0 (iPhone; CPU iPhone OS 18_7 like Mac OS X) AppleWebKit/605.1.15 (KHTML, like Gecko) Version/26.3 Mobile/15E148 Safari/604.1 | L7: mobile | M7: 329f3f0d-df3f-4745-8c8c-9d423832d55c | N7: NO
A8: 46116.796 | B8: page_view | D8: /userCodeAppPanel | E8: linkedin | F8: social | G8: portal_busquedas | J8: https://n-h2l2qss2sclrg4n74cjzkbuuq76zyb6l2fgpgeq-1lu-script.googleusercontent.com/ | K8: Mozilla/5.0 (Macintosh; Intel Mac OS X 10_15_7) AppleWebKit/605.1.15 (KHTML, like Gecko) Version/17.6 Safari/605.1.15 | L8: desktop | M8: c0affd1a-f0e3-4a7e-82e0-0a2a342c81f1 | N8: NO
A9: 46116.743 | B9: page_view | D9: /portal-busquedas/ | K9: Mozilla/5.0 (iPhone; CPU iPhone OS 18_7 like Mac OS X) AppleWebKit/605.1.15 (KHTML, like Gecko) Version/26.3 Mobile/15E148 Safari/604.1 | L9: mobile | M9: a1fe4cdf-977c-4826-bc8c-6ec6f79e34bd | N9: NO
A10: 46116.592 | B10: view_job | C10: JOB-2025-000039 | D10: /portal-busquedas/ | J10: https://www.linkedin.com/ | K10: Mozilla/5.0 (iPhone; CPU iPhone OS 18_7 like Mac OS X) AppleWebKit/605.1.15 (KHTML, like Gecko) Mobile/15E148 [LinkedInApp]/9.31.9671 | L10: mobile | M10: ce11f1a5-7cfe-4a23-9791-fad6c3cc7722 | N10: SI
A11: 46116.592 | B11: view_job | C11: JOB-2025-000039 | D11: /portal-busquedas/ | J11: https://www.linkedin.com/ | K11: Mozilla/5.0 (iPhone; CPU iPhone OS 18_7 like Mac OS X) AppleWebKit/605.1.15 (KHTML, like Gecko) Mobile/15E148 [LinkedInApp]/9.31.9671 | L11: mobile | M11: ce11f1a5-7cfe-4a23-9791-fad6c3cc7722 | N11: SI
A12: 46116.592 | B12: view_job | C12: JOB-2025-000039 | D12: /portal-busquedas/ | J12: https://www.linkedin.com/ | K12: Mozilla/5.0 (iPhone; CPU iPhone OS 18_7 like Mac OS X) AppleWebKit/605.1.15 (KHTML, like Gecko) Mobile/15E148 [LinkedInApp]/9.31.9671 | L12: mobile | M12: ce11f1a5-7cfe-4a23-9791-fad6c3cc7722 | N12: SI
A13: 46116.592 | B13: view_job | C13: JOB-2025-000039 | D13: /portal-busquedas/ | J13: https://www.linkedin.com/ | K13: Mozilla/5.0 (iPhone; CPU iPhone OS 18_7 like Mac OS X) AppleWebKit/605.1.15 (KHTML, like Gecko) Mobile/15E148 [LinkedInApp]/9.31.9671 | L13: mobile | M13: ce11f1a5-7cfe-4a23-9791-fad6c3cc7722 | N13: SI
A14: 46116.592 | B14: view_job | C14: JOB-2025-000039 | D14: /portal-busquedas/ | J14: https://www.linkedin.com/ | K14: Mozilla/5.0 (iPhone; CPU iPhone OS 18_7 like Mac OS X) AppleWebKit/605.1.15 (KHTML, like Gecko) Mobile/15E148 [LinkedInApp]/9.31.9671 | L14: mobile | M14: ce11f1a5-7cfe-4a23-9791-fad6c3cc7722 | N14: SI
A15: 46116.59 | B15: view_job | C15: JOB-2025-000039 | D15: /portal-busquedas/ | J15: https://www.linkedin.com/ | K15: Mozilla/5.0 (iPhone; CPU iPhone OS 18_7 like Mac OS X) AppleWebKit/605.1.15 (KHTML, like Gecko) Mobile/15E148 [LinkedInApp]/9.31.9671 | L15: mobile | M15: ce11f1a5-7cfe-4a23-9791-fad6c3cc7722 | N15: SI
A16: 46116.59 | B16: view_job | C16: JOB-2025-000039 | D16: /portal-busquedas/ | J16: https://www.linkedin.com/ | K16: Mozilla/5.0 (iPhone; CPU iPhone OS 18_7 like Mac OS X) AppleWebKit/605.1.15 (KHTML, like Gecko) Mobile/15E148 [LinkedInApp]/9.31.9671 | L16: mobile | M16: ce11f1a5-7cfe-4a23-9791-fad6c3cc7722 | N16: SI
A17: 46116.589 | B17: page_view | D17: /portal-busquedas/ | J17: https://www.linkedin.com/ | K17: Mozilla/5.0 (iPhone; CPU iPhone OS 18_7 like Mac OS X) AppleWebKit/605.1.15 (KHTML, like Gecko) Mobile/15E148 [LinkedInApp]/9.31.9671 | L17: mobile | M17: ce11f1a5-7cfe-4a23-9791-fad6c3cc7722 | N17: SI
A18: 46116.553 | B18: view_job | C18: JOB-2025-000002 | D18: /portal-busquedas/ | J18: https://www.linkedin.com/ | K18: Mozilla/5.0 (Windows NT 10.0; Win64; x64) AppleWebKit/537.36 (KHTML, like Gecko) Chrome/146.0.0.0 Safari/537.36 | L18: desktop | M18: 2189dd8f-cbb9-4709-abdc-7a2e951b8e26 | N18: NO
A19: 46116.553 | B19: page_view | D19: /portal-busquedas/ | J19: https://www.linkedin.com/ | K19: Mozilla/5.0 (Windows NT 10.0; Win64; x64) AppleWebKit/537.36 (KHTML, like Gecko) Chrome/146.0.0.0 Safari/537.36 | L19: desktop | M19: 2189dd8f-cbb9-4709-abdc-7a2e951b8e26 | N19: NO
A20: 46116.453 | B20: page_view | D20: /portal-busquedas/ | K20: Mozilla/5.0 (Windows NT 10.0; Win64; x64) AppleWebKit/537.36 (KHTML, like Gecko) Chrome/146.0.0.0 Safari/537.36 | L20: desktop | M20: 221accbe-9136-46ef-a594-f0a61ff5d5f3 | N20: NO
A21: 46116.449 | B21: view_job | C21: JOB-2025-000040 | D21: /portal-busquedas/ | J21: https://www.linkedin.com/ | K21: Mozilla/5.0 (Windows NT 10.0; Win64; x64) AppleWebKit/537.36 (KHTML, like Gecko) Chrome/146.0.0.0 Safari/537.36 | L21: desktop | M21: 7ae277ed-2fee-4310-8619-eca76a170b20 | N21: NO
A22: 46116.448 | B22: view_job | C22: JOB-2025-000010 | D22: /portal-busquedas/ | J22: https://www.linkedin.com/ | K22: Mozilla/5.0 (Windows NT 10.0; Win64; x64) AppleWebKit/537.36 (KHTML, like Gecko) Chrome/146.0.0.0 Safari/537.36 | L22: desktop | M22: 7ae277ed-2fee-4310-8619-eca76a170b20 | N22: NO
A23: 46116.448 | B23: page_view | D23: /portal-busquedas/ | J23: https://www.linkedin.com/ | K23: Mozilla/5.0 (Windows NT 10.0; Win64; x64) AppleWebKit/537.36 (KHTML, like Gecko) Chrome/146.0.0.0 Safari/537.36 | L23: desktop | M23: 7ae277ed-2fee-4310-8619-eca76a170b20 | N23: NO
A24: 46116.439 | B24: view_job | C24: JOB-2025-000029 | D24: /portal-busquedas/ | J24: https://www.linkedin.com/ | K24: Mozilla/5.0 (Windows NT 10.0; Win64; x64) AppleWebKit/537.36 (KHTML, like Gecko) Chrome/146.0.0.0 Safari/537.36 | L24: desktop | M24: 5d652398-ea5d-4857-8551-49a29e2f4fe9 | N24: NO
A25: 46116.439 | B25: view_job | C25: JOB-2025-000011 | D25: /portal-busquedas/ | J25: https://www.linkedin.com/ | K25: Mozilla/5.0 (Windows NT 10.0; Win64; x64) AppleWebKit/537.36 (KHTML, like Gecko) Chrome/146.0.0.0 Safari/537.36 | L25: desktop | M25: 5d652398-ea5d-4857-8551-49a29e2f4fe9 | N25: NO
A26: 46116.439 | B26: view_job | C26: JOB-2025-000029 | D26: /portal-busquedas/ | J26: https://www.linkedin.com/ | K26: Mozilla/5.0 (Windows NT 10.0; Win64; x64) AppleWebKit/537.36 (KHTML, like Gecko) Chrome/146.0.0.0 Safari/537.36 | L26: desktop | M26: 5d652398-ea5d-4857-8551-49a29e2f4fe9 | N26: NO
A27: 46116.439 | B27: view_job | C27: JOB-2025-000030 | D27: /portal-busquedas/ | J27: https://www.linkedin.com/ | K27: Mozilla/5.0 (Windows NT 10.0; Win64; x64) AppleWebKit/537.36 (KHTML, like Gecko) Chrome/146.0.0.0 Safari/537.36 | L27: desktop | M27: 5d652398-ea5d-4857-8551-49a29e2f4fe9 | N27: NO
A28: 46116.437 | B28: view_job | C28: JOB-2025-000039 | D28: /portal-busquedas/ | J28: https://www.linkedin.com/ | K28: Mozilla/5.0 (Windows NT 10.0; Win64; x64) AppleWebKit/537.36 (KHTML, like Gecko) Chrome/146.0.0.0 Safari/537.36 | L28: desktop | M28: 5d652398-ea5d-4857-8551-49a29e2f4fe9 | N28: NO
A29: 46116.437 | B29: view_job | C29: JOB-2025-000040 | D29: /portal-busquedas/ | J29: https://www.linkedin.com/ | K29: Mozilla/5.0 (Windows NT 10.0; Win64; x64) AppleWebKit/537.36 (KHTML, like Gecko) Chrome/146.0.0.0 Safari/537.36 | L29: desktop | M29: 5d652398-ea5d-4857-8551-49a29e2f4fe9 | N29: NO
A30: 46116.437 | B30: view_job | C30: JOB-2025-000039 | D30: /portal-busquedas/ | J30: https://www.linkedin.com/ | K30: Mozilla/5.0 (Windows NT 10.0; Win64; x64) AppleWebKit/537.36 (KHTML, like Gecko) Chrome/146.0.0.0 Safari/537.36 | L30: desktop | M30: 5d652398-ea5d-4857-8551-49a29e2f4fe9 | N30: NO
A31: 46116.437 | B31: view_job | C31: JOB-2025-000038 | D31: /portal-busquedas/ | J31: https://www.linkedin.com/ | K31: Mozilla/5.0 (Windows NT 10.0; Win64; x64) AppleWebKit/537.36 (KHTML, like Gecko) Chrome/146.0.0.0 Safari/537.36 | L31: desktop | M31: 5d652398-ea5d-4857-8551-49a29e2f4fe9 | N31: NO
A32: 46116.437 | B32: view_job | C32: JOB-2025-000036 | D32: /portal-busquedas/ | J32: https://www.linkedin.com/ | K32: Mozilla/5.0 (Windows NT 10.0; Win64; x64) AppleWebKit/537.36 (KHTML, like Gecko) Chrome/146.0.0.0 Safari/537.36 | L32: desktop | M32: 5d652398-ea5d-4857-8551-49a29e2f4fe9 | N32: NO
A33: 46116.436 | B33: view_job | C33: JOB-2025-000035 | D33: /portal-busquedas/ | J33: https://www.linkedin.com/ | K33: Mozilla/5.0 (Windows NT 10.0; Win64; x64) AppleWebKit/537.36 (KHTML, like Gecko) Chrome/146.0.0.0 Safari/537.36 | L33: desktop | M33: 5d652398-ea5d-4857-8551-49a29e2f4fe9 | N33: NO
A34: 46116.436 | B34: view_job | C34: JOB-2025-000034 | D34: /portal-busquedas/ | J34: https://www.linkedin.com/ | K34: Mozilla/5.0 (Windows NT 10.0; Win64; x64) AppleWebKit/537.36 (KHTML, like Gecko) Chrome/146.0.0.0 Safari/537.36 | L34: desktop | M34: 5d652398-ea5d-4857-8551-49a29e2f4fe9 | N34: NO
A35: 46116.436 | B35: view_job | C35: JOB-2025-000033 | D35: /portal-busquedas/ | J35: https://www.linkedin.com/ | K35: Mozilla/5.0 (Windows NT 10.0; Win64; x64) AppleWebKit/537.36 (KHTML, like Gecko) Chrome/146.0.0.0 Safari/537.36 | L35: desktop | M35: 5d652398-ea5d-4857-8551-49a29e2f4fe9 | N35: NO
... A50: 46116.435 | B50: view_job | C50: JOB-2025-000025 | D50: /portal-busquedas/ | J50: https://www.linkedin.com/ | K50: Mozilla/5.0 (Windows NT 10.0; Win64; x64) AppleWebKit/537.36 (KHTML, like Gecko) Chrome/146.0.0.0 Safari/537.36 | L50: desktop | M50: 5d652398-ea5d-4857-8551-49a29e2f4fe9 | N50: NO
A51: 46116.431 | B51: page_view | D51: /portal-busquedas/ | J51: https://lnkd.in/ | K51: Mozilla/5.0 (iPhone; CPU iPhone OS 18_7 like Mac OS X) AppleWebKit/605.1.15 (KHTML, like Gecko) Version/26.3 Mobile/15E148 Safari/604.1 | L51: mobile | M51: e3df9c93-0258-4d2d-ad17-e4ea3c4a922e | N51: SI
A52: 46116.407 | B52: page_view | D52: /portal-busquedas/ | J52: https://www.linkedin.com/ | K52: Mozilla/5.0 (Windows NT 10.0; Win64; x64) AppleWebKit/537.36 (KHTML, like Gecko) Chrome/146.0.0.0 Safari/537.36 | L52: desktop | M52: 5d652398-ea5d-4857-8551-49a29e2f4fe9 | N52: NO
A53: 46116.405 | B53: page_view | D53: /portal-busquedas/ | K53: Mozilla/5.0 (X11; Linux x86_64) AppleWebKit/537.36 (KHTML, like Gecko) Chrome/116.0.0.0 Safari/537.36 | L53: desktop | M53: fc9df8a1-f5f2-4c63-9e84-76e363f79190 | N53: NO
A54: 46115.981 | B54: page_view | D54: /portal-busquedas/ | K54: Mozilla/5.0 (iPhone; CPU iPhone OS 18_7_1 like Mac OS X) AppleWebKit/605.1.15 (KHTML, like Gecko) Version/18.7 Mobile/15E148 Safari/604.1 | L54: mobile | M54: 480b64a8-58b8-46b3-8eb5-a24fd5e66e61 | N54: NO
A55: 46115.879 | B55: view_job | C55: JOB-2025-000037 | D55: /portal-busquedas/ | K55: Mozilla/5.0 (iPhone; CPU iPhone OS 18_6_2 like Mac OS X) AppleWebKit/605.1.15 (KHTML, like Gecko) Version/18.6 Mobile/15E148 Safari/604.1 | L55: mobile | M55: daf7a86f-79b1-4d72-85a3-0dee65e7727f | N55: NO
A56: 46115.879 | B56: view_job | C56: JOB-2025-000037 | D56: /portal-busquedas/ | K56: Mozilla/5.0 (iPhone; CPU iPhone OS 18_6_2 like Mac OS X) AppleWebKit/605.1.15 (KHTML, like Gecko) Version/18.6 Mobile/15E148 Safari/604.1 | L56: mobile | M56: daf7a86f-79b1-4d72-85a3-0dee65e7727f | N56: NO
A57: 46115.879 | B57: view_job | C57: JOB-2025-000037 | D57: /portal-busquedas/ | K57: Mozilla/5.0 (iPhone; CPU iPhone OS 18_6_2 like Mac OS X) AppleWebKit/605.1.15 (KHTML, like Gecko) Version/18.6 Mobile/15E148 Safari/604.1 | L57: mobile | M57: daf7a86f-79b1-4d72-85a3-0dee65e7727f | N57: NO
A58: 46115.878 | B58: page_view | D58: /portal-busquedas/ | K58: Mozilla/5.0 (iPhone; CPU iPhone OS 18_6_2 like Mac OS X) AppleWebKit/605.1.15 (KHTML, like Gecko) Version/18.6 Mobile/15E148 Safari/604.1 | L58: mobile | M58: daf7a86f-79b1-4d72-85a3-0dee65e7727f | N58: NO
A59: 46115.874 | B59: apply_click | C59: JOB-2025-000037 | D59: /portal-busquedas/ | K59: Mozilla/5.0 (Linux; Android 10; K) AppleWebKit/537.36 (KHTML, like Gecko) Chrome/146.0.0.0 Mobile Safari/537.36 | L59: mobile | M59: 77f62e64-7faa-417d-a889-0274fa1c58c4 | N59: NO
A60: 46115.874 | B60: view_job | C60: JOB-2025-000038 | D60: /portal-busquedas/ | K60: Mozilla/5.0 (Linux; Android 10; K) AppleWebKit/537.36 (KHTML, like Gecko) Chrome/146.0.0.0 Mobile Safari/537.36 | L60: mobile | M60: 77f62e64-7faa-417d-a889-0274fa1c58c4 | N60: NO
A61: 46115.874 | B61: apply_click | C61: JOB-2025-000038 | D61: /portal-busquedas/ | K61: Mozilla/5.0 (Linux; Android 10; K) AppleWebKit/537.36 (KHTML, like Gecko) Chrome/146.0.0.0 Mobile Safari/537.36 | L61: mobile | M61: 77f62e64-7faa-417d-a889-0274fa1c58c4 | N61: NO
A62: 46115.873 | B62: page_view | D62: /portal-busquedas/ | K62: Mozilla/5.0 (Linux; Android 10; K) AppleWebKit/537.36 (KHTML, like Gecko) Chrome/146.0.0.0 Mobile Safari/537.36 | L62: mobile | M62: 77f62e64-7faa-417d-a889-0274fa1c58c4 | N62: NO
A63: 46115.862 | B63: view_job | C63: JOB-2025-000029 | D63: /portal-busquedas/ | J63: android-app://com.linkedin.android/ | K63: Mozilla/5.0 (Linux; Android 10; K) AppleWebKit/537.36 (KHTML, like Gecko) Chrome/146.0.0.0 Mobile Safari/537.36 | L63: mobile | M63: 70be6e03-7d7a-4265-8c69-59a73ebf62d6 | N63: SI
A64: 46115.861 | B64: page_view | D64: /portal-busquedas/ | J64: android-app://com.linkedin.android/ | K64: Mozilla/5.0 (Linux; Android 10; K) AppleWebKit/537.36 (KHTML, like Gecko) Chrome/146.0.0.0 Mobile Safari/537.36 | L64: mobile | M64: 70be6e03-7d7a-4265-8c69-59a73ebf62d6 | N64: SI
A65: 46115.861 | B65: view_job | C65: JOB-2025-000019 | D65: /portal-busquedas/ | J65: android-app://com.linkedin.android/ | K65: Mozilla/5.0 (Linux; Android 10; K) AppleWebKit/537.36 (KHTML, like Gecko) Chrome/146.0.0.0 Mobile Safari/537.36 | L65: mobile | M65: 70be6e03-7d7a-4265-8c69-59a73ebf62d6 | N65: SI
A66: 46115.861 | B66: page_view | D66: /portal-busquedas/ | J66: android-app://com.linkedin.android/ | K66: Mozilla/5.0 (Linux; Android 10; K) AppleWebKit/537.36 (KHTML, like Gecko) Chrome/146.0.0.0 Mobile Safari/537.36 | L66: mobile | M66: 70be6e03-7d7a-4265-8c69-59a73ebf62d6 | N66: SI
A67: 46115.861 | B67: view_job | C67: JOB-2025-000011 | D67: /portal-busquedas/ | J67: android-app://com.linkedin.android/ | K67: Mozilla/5.0 (Linux; Android 10; K) AppleWebKit/537.36 (KHTML, like Gecko) Chrome/146.0.0.0 Mobile Safari/537.36 | L67: mobile | M67: 70be6e03-7d7a-4265-8c69-59a73ebf62d6 | N67: SI
A68: 46115.861 | B68: view_job | C68: JOB-2025-000011 | D68: /portal-busquedas/ | J68: android-app://com.linkedin.android/ | K68: Mozilla/5.0 (Linux; Android 10; K) AppleWebKit/537.36 (KHTML, like Gecko) Chrome/146.0.0.0 Mobile Safari/537.36 | L68: mobile | M68: 70be6e03-7d7a-4265-8c69-59a73ebf62d6 | N68: SI
A69: 46115.86 | B69: page_view | D69: /portal-busquedas/ | J69: android-app://com.linkedin.android/ | K69: Mozilla/5.0 (Linux; Android 10; K) AppleWebKit/537.36 (KHTML, like Gecko) Chrome/146.0.0.0 Mobile Safari/537.36 | L69: mobile | M69: 70be6e03-7d7a-4265-8c69-59a73ebf62d6 | N69: SI
A70: 46115.843 | B70: apply_click | C70: JOB-2025-000037,JOB-2025-000038 | D70: /portal-busquedas/ | K70: Mozilla/5.0 (Windows NT 10.0; Win64; x64) AppleWebKit/537.36 (KHTML, like Gecko) Chrome/145.0.0.0 Safari/537.36 Avast/145.0.34271.162 | L70: desktop | M70: 78c13185-8b46-46a1-bd43-5a546df98932 | N70: NO
A71: 46115.842 | B71: view_job | C71: JOB-2025-000038 | D71: /portal-busquedas/ | K71: Mozilla/5.0 (Windows NT 10.0; Win64; x64) AppleWebKit/537.36 (KHTML, like Gecko) Chrome/145.0.0.0 Safari/537.36 Avast/145.0.34271.162 | L71: desktop | M71: 78c13185-8b46-46a1-bd43-5a546df98932 | N71: NO
A72: 46115.842 | B72: page_view | D72: /portal-busquedas/ | K72: Mozilla/5.0 (Windows NT 10.0; Win64; x64) AppleWebKit/537.36 (KHTML, like Gecko) Chrome/145.0.0.0 Safari/537.36 Avast/145.0.34271.162 | L72: desktop | M72: 78c13185-8b46-46a1-bd43-5a546df98932 | N72: NO
A73: 46115.838 | B73: apply_click | C73: JOB-2025-000037,JOB-2025-000038 | D73: /portal-busquedas/ | J73: https://www.linkedin.com/ | K73: Mozilla/5.0 (Windows NT 10.0; Win64; x64) AppleWebKit/537.36 (KHTML, like Gecko) Chrome/146.0.0.0 Safari/537.36 | L73: desktop | M73: 704f0e60-0fa7-4910-bbd3-1eeae551feac | N73: NO
A74: 46115.837 | B74: view_job | C74: JOB-2025-000037 | D74: /portal-busquedas/ | J74: https://www.linkedin.com/ | K74: Mozilla/5.0 (Windows NT 10.0; Win64; x64) AppleWebKit/537.36 (KHTML, like Gecko) Chrome/146.0.0.0 Safari/537.36 | L74: desktop | M74: 704f0e60-0fa7-4910-bbd3-1eeae551feac | N74: NO
A75: 46115.837 | B75: page_view | D75: /portal-busquedas/ | J75: https://www.linkedin.com/ | K75: Mozilla/5.0 (Windows NT 10.0; Win64; x64) AppleWebKit/537.36 (KHTML, like Gecko) Chrome/146.0.0.0 Safari/537.36 | L75: desktop | M75: 704f0e60-0fa7-4910-bbd3-1eeae551feac | N75: NO
A76: 46115.817 | B76: page_view | D76: /portal-busquedas/ | J76: https://www.linkedin.com/ | K76: Mozilla/5.0 (iPhone; CPU iPhone OS 18_7 like Mac OS X) AppleWebKit/605.1.15 (KHTML, like Gecko) Mobile/15E148 [LinkedInApp]/9.31.9671 | L76: mobile | M76: 778b7fe4-4704-455c-894e-85f729ecbba6 | N76: SI
A77: 46115.811 | B77: page_view | D77: /portal-busquedas/ | K77: Mozilla/5.0 (iPhone; CPU iPhone OS 18_7 like Mac OS X) AppleWebKit/605.1.15 (KHTML, like Gecko) Version/26.3 Mobile/15E148 Safari/604.1 | L77: mobile | M77: a765e25b-7ae1-4e30-9d90-2dabc1626d80 | N77: NO
A78: 46115.791 | B78: page_view | D78: /portal-busquedas/ | J78: https://www.linkedin.com/ | K78: Mozilla/5.0 (iPhone; CPU iPhone OS 18_7 like Mac OS X) AppleWebKit/605.1.15 (KHTML, like Gecko) Mobile/15E148 [LinkedInApp]/9.31.9671 | L78: mobile | M78: 778b7fe4-4704-455c-894e-85f729ecbba6 | N78: NO
A79: 46115.784 | B79: page_view | D79: /portal-busquedas/ | J79: https://www.linkedin.com/ | K79: Mozilla/5.0 (iPhone; CPU iPhone OS 18_7 like Mac OS X) AppleWebKit/605.1.15 (KHTML, like Gecko) Mobile/15E148 [LinkedInApp]/9.31.9440.4 | L79: mobile | M79: 5cbfaf5a-2019-4b6d-953d-878fe028cd5c | N79: NO
A80: 46115.774 | B80: apply_click | C80: JOB-2025-000037 | D80: /portal-busquedas/ | K80: Mozilla/5.0 (Linux; Android 10; K) AppleWebKit/537.36 (KHTML, like Gecko) Chrome/146.0.0.0 Mobile Safari/537.36 | L80: mobile | M80: 92f4a39d-a71a-4f4a-9d5c-dccc9fec4f2b | N80: NO
A81: 46115.773 | B81: page_view | D81: /portal-busquedas/ | K81: Mozilla/5.0 (Linux; Android 10; K) AppleWebKit/537.36 (KHTML, like Gecko) Chrome/146.0.0.0 Mobile Safari/537.36 | L81: mobile | M81: 92f4a39d-a71a-4f4a-9d5c-dccc9fec4f2b | N81: NO
A82: 46115.756 | B82: page_view | D82: /userCodeAppPanel | E82: linkedin | F82: social | G82: portal_busquedas | J82: https://n-h2l2qss2sclrg4n74cjzkbuuq76zyb6l2fgpgeq-0lu-script.googleusercontent.com/ | K82: Mozilla/5.0 (iPhone; CPU iPhone OS 18_7 like Mac OS X) AppleWebKit/605.1.15 (KHTML, like Gecko) Version/26.3 Mobile/15E148 Safari/604.1 | L82: mobile | M82: 191d005c-56a3-4925-9ddb-a365aceb3d45 | N82: NO
A83: 46115.741 | B83: page_view | D83: /portal-busquedas/ | K83: Mozilla/5.0 (Linux; Android 10; K) AppleWebKit/537.36 (KHTML, like Gecko) Chrome/138.0.0.0 Mobile Safari/537.36 (compatible; Google-Read-Aloud; +https://support.google.com/webmasters/answer/1061943) | L83: mobile | M83: ceadfe2f-794c-4b25-a37a-b8218c7b50cb | N83: NO
A84: 46115.741 | B84: page_view | D84: /portal-busquedas/ | K84: Mozilla/5.0 (Linux; Android 10; K) AppleWebKit/537.36 (KHTML, like Gecko) Chrome/146.0.0.0 Mobile Safari/537.36 | L84: mobile | M84: 2b0393fe-f850-4733-9de2-f5051d00c9ac | N84: NO
A85: 46115.731 | B85: view_job | C85: JOB-2025-000032 | D85: /portal-busquedas/ | J85: https://www.linkedin.com/ | K85: Mozilla/5.0 (iPhone; CPU iPhone OS 18_5 like Mac OS X) AppleWebKit/605.1.15 (KHTML, like Gecko) Mobile/15E148 [LinkedInApp]/9.31.7550 | L85: mobile | M85: 483eb7f5-2cf1-4a95-8073-9f4b9d747366 | N85: NO
A86: 46115.731 | B86: page_view | D86: /portal-busquedas/ | J86: https://www.linkedin.com/ | K86: Mozilla/5.0 (iPhone; CPU iPhone OS 18_5 like Mac OS X) AppleWebKit/605.1.15 (KHTML, like Gecko) Mobile/15E148 [LinkedInApp]/9.31.7550 | L86: mobile | M86: 483eb7f5-2cf1-4a95-8073-9f4b9d747366 | N86: NO
A87: 46115.706 | B87: apply_click | C87: JOB-2025-000037 | D87: /portal-busquedas/ | J87: https://lnkd.in/ | K87: Mozilla/5.0 (iPhone; CPU iPhone OS 18_7 like Mac OS X) AppleWebKit/605.1.15 (KHTML, like Gecko) Version/26.3 Mobile/15E148 Safari/604.1 | L87: mobile | M87: e3df9c93-0258-4d2d-ad17-e4ea3c4a922e | N87: SI
A88: 46115.679 | B88: view_job | C88: JOB-2025-000037 | D88: /portal-busquedas/ | J88: https://lnkd.in/ | K88: Mozilla/5.0 (iPhone; CPU iPhone OS 18_7 like Mac OS X) AppleWebKit/605.1.15 (KHTML, like Gecko) Version/26.3 Mobile/15E148 Safari/604.1 | L88: mobile | M88: e3df9c93-0258-4d2d-ad17-e4ea3c4a922e | N88: SI
A89: 46115.679 | B89: view_job | C89: JOB-2025-000001 | D89: /portal-busquedas/ | J89: https://lnkd.in/ | K89: Mozilla/5.0 (iPhone; CPU iPhone OS 18_7 like Mac OS X) AppleWebKit/605.1.15 (KHTML, like Gecko) Version/26.3 Mobile/15E148 Safari/604.1 | L89: mobile | M89: e3df9c93-0258-4d2d-ad17-e4ea3c4a922e | N89: SI
A90: 46115.679 | B90: page_view | D90: /portal-busquedas/ | J90: https://lnkd.in/ | K90: Mozilla/5.0 (iPhone; CPU iPhone OS 18_7 like Mac OS X) AppleWebKit/605.1.15 (KHTML, like Gecko) Version/26.3 Mobile/15E148 Safari/604.1 | L90: mobile | M90: e3df9c93-0258-4d2d-ad17-e4ea3c4a922e | N90: SI
A91: 46115.678 | B91: view_job | C91: JOB-2025-000037 | D91: /portal-busquedas/ | J91: https://lnkd.in/ | K91: Mozilla/5.0 (iPhone; CPU iPhone OS 18_7 like Mac OS X) AppleWebKit/605.1.15 (KHTML, like Gecko) Version/26.3 Mobile/15E148 Safari/604.1 | L91: mobile | M91: e3df9c93-0258-4d2d-ad17-e4ea3c4a922e | N91: NO
A92: 46115.678 | B92: view_job | C92: JOB-2025-000037 | D92: /portal-busquedas/ | J92: https://lnkd.in/ | K92: Mozilla/5.0 (iPhone; CPU iPhone OS 18_7 like Mac OS X) AppleWebKit/605.1.15 (KHTML, like Gecko) Version/26.3 Mobile/15E148 Safari/604.1 | L92: mobile | M92: e3df9c93-0258-4d2d-ad17-e4ea3c4a922e | N92: NO
A93: 46115.677 | B93: page_view | D93: /portal-busquedas/ | J93: https://lnkd.in/ | K93: Mozilla/5.0 (iPhone; CPU iPhone OS 18_7 like Mac OS X) AppleWebKit/605.1.15 (KHTML, like Gecko) Version/26.3 Mobile/15E148 Safari/604.1 | L93: mobile | M93: e3df9c93-0258-4d2d-ad17-e4ea3c4a922e | N93: NO
A94: 46115.673 | B94: view_job | C94: JOB-2025-000008 | D94: /portal-busquedas/ | J94: https://www.linkedin.com/ | K94: Mozilla/5.0 (Windows NT 10.0; Win64; x64) AppleWebKit/537.36 (KHTML, like Gecko) Chrome/147.0.0.0 Safari/537.36 | L94: desktop | M94: 08a36feb-940f-409b-b8a9-30dfe61aec3f | N94: NO
A95: 46115.673 | B95: view_job | C95: JOB-2025-000010 | D95: /portal-busquedas/ | J95: https://www.linkedin.com/ | K95: Mozilla/5.0 (Windows NT 10.0; Win64; x64) AppleWebKit/537.36 (KHTML, like Gecko) Chrome/147.0.0.0 Safari/537.36 | L95: desktop | M95: 08a36feb-940f-409b-b8a9-30dfe61aec3f | N95: NO
A96: 46115.672 | B96: page_view | D96: /portal-busquedas/ | J96: https://www.linkedin.com/ | K96: Mozilla/5.0 (Windows NT 10.0; Win64; x64) AppleWebKit/537.36 (KHTML, like Gecko) Chrome/147.0.0.0 Safari/537.36 | L96: desktop | M96: 08a36feb-940f-409b-b8a9-30dfe61aec3f | N96: NO
A97: 46115.649 | B97: page_view | D97: /portal-busquedas/ | K97: Mozilla/5.0 (iPhone; CPU iPhone OS 18_7 like Mac OS X) AppleWebKit/605.1.15 (KHTML, like Gecko) Version/26.3 Mobile/15E148 Safari/604.1 | L97: mobile | M97: dcea3389-b57f-4aca-9561-6e4fa8270d26 | N97: NO
A98: 46115.628 | B98: view_job | C98: JOB-2025-000008 | D98: /portal-busquedas/ | J98: https://lnkd.in/ | K98: Mozilla/5.0 (Windows NT 10.0; Win64; x64) AppleWebKit/537.36 (KHTML, like Gecko) Chrome/146.0.0.0 Safari/537.36 Edg/146.0.0.0 | L98: desktop | M98: 885db93e-67c5-4da0-9f84-d85284b20932 | N98: NO
A99: 46115.628 | B99: page_view | D99: /portal-busquedas/ | J99: https://lnkd.in/ | K99: Mozilla/5.0 (Windows NT 10.0; Win64; x64) AppleWebKit/537.36 (KHTML, like Gecko) Chrome/146.0.0.0 Safari/537.36 Edg/146.0.0.0 | L99: desktop | M99: 885db93e-67c5-4da0-9f84-d85284b20932 | N99: NO
A100: 46115.606 | B100: page_view | D100: /portal-busquedas/ | K100: Mozilla/5.0 (Linux; Android 10; K) AppleWebKit/537.36 (KHTML, like Gecko) SamsungBrowser/29.0 Chrome/136.0.0.0 Mobile Safari/537.36 | L100: mobile | M100: 1266cf29-fab6-4f7a-a323-3f08f4e056eb | N100: NO
A101: 46115.575 | B101: view_job | C101: JOB-2025-000037 | D101: /portal-busquedas/ | J101: https://www.linkedin.com/ | K101: Mozilla/5.0 (Windows NT 10.0; Win64; x64) AppleWebKit/537.36 (KHTML, like Gecko) Chrome/146.0.0.0 Safari/537.36 | L101: desktop | M101: 640a2b9a-752a-4ed4-8c81-adf396cb15af | N101: NO
A102: 46115.575 | B102: apply_click | C102: JOB-2025-000038 | D102: /portal-busquedas/ | J102: https://www.linkedin.com/ | K102: Mozilla/5.0 (Windows NT 10.0; Win64; x64) AppleWebKit/537.36 (KHTML, like Gecko) Chrome/146.0.0.0 Safari/537.36 | L102: desktop | M102: 640a2b9a-752a-4ed4-8c81-adf396cb15af | N102: NO
A103: 46115.575 | B103: view_job | C103: JOB-2025-000038 | D103: /portal-busquedas/ | J103: https://www.linkedin.com/ | K103: Mozilla/5.0 (Windows NT 10.0; Win64; x64) AppleWebKit/537.36 (KHTML, like Gecko) Chrome/146.0.0.0 Safari/537.36 | L103: desktop | M103: 640a2b9a-752a-4ed4-8c81-adf396cb15af | N103: NO
A104: 46115.574 | B104: page_view | D104: /portal-busquedas/ | J104: https://www.linkedin.com/ | K104: Mozilla/5.0 (Windows NT 10.0; Win64; x64) AppleWebKit/537.36 (KHTML, like Gecko) Chrome/146.0.0.0 Safari/537.36 | L104: desktop | M104: 640a2b9a-752a-4ed4-8c81-adf396cb15af | N104: NO
A105: 46115.574 | B105: page_view | D105: /portal-busquedas/ | J105: https://lnkd.in/ | K105: Mozilla/5.0 (iPhone; CPU iPhone OS 18_6_2 like Mac OS X) AppleWebKit/605.1.15 (KHTML, like Gecko) Version/18.6 Mobile/15E148 Safari/604.1 | L105: mobile | M105: a9e6e082-e689-4b6e-aed0-ebce0a18affd | N105: SI
A106: 46115.574 | B106: page_view | D106: /portal-busquedas/ | J106: https://lnkd.in/ | K106: Mozilla/5.0 (iPhone; CPU iPhone OS 18_6_2 like Mac OS X) AppleWebKit/605.1.15 (KHTML, like Gecko) Version/18.6 Mobile/15E148 Safari/604.1 | L106: mobile | M106: a9e6e082-e689-4b6e-aed0-ebce0a18affd | N106: NO
A107: 46115.563 | B107: apply_click | C107: JOB-2025-000037 | D107: /portal-busquedas/ | J107: https://www.linkedin.com/ | K107: Mozilla/5.0 (iPhone; CPU iPhone OS 18_7 like Mac OS X) AppleWebKit/605.1.15 (KHTML, like Gecko) Mobile/15E148 [LinkedInApp]/9.31.9671 | L107: mobile | M107: 667ddf00-1a76-4565-bfbb-5af388c486b0 | N107: NO
A108: 46115.563 | B108: page_view | D108: /portal-busquedas/ | J108: https://www.linkedin.com/ | K108: Mozilla/5.0 (iPhone; CPU iPhone OS 18_7 like Mac OS X) AppleWebKit/605.1.15 (KHTML, like Gecko) Mobile/15E148 [LinkedInApp]/9.31.9671 | L108: mobile | M108: 667ddf00-1a76-4565-bfbb-5af388c486b0 | N108: NO
A109: 46115.557 | B109: apply_click | C109: JOB-2025-000037 | D109: /portal-busquedas/ | J109: https://lnkd.in/ | K109: Mozilla/5.0 (iPhone; CPU iPhone OS 18_7 like Mac OS X) AppleWebKit/605.1.15 (KHTML, like Gecko) Version/26.3 Mobile/15E148 Safari/604.1 | L109: mobile | M109: ce2bc13b-932d-4f6b-a146-c57a3695ac57 | N109: NO
A110: 46115.556 | B110: page_view | D110: /portal-busquedas/ | J110: https://lnkd.in/ | K110: Mozilla/5.0 (iPhone; CPU iPhone OS 18_7 like Mac OS X) AppleWebKit/605.1.15 (KHTML, like Gecko) Version/26.3 Mobile/15E148 Safari/604.1 | L110: mobile | M110: ce2bc13b-932d-4f6b-a146-c57a3695ac57 | N110: NO
A111: 46115.547 | B111: apply_click | C111: JOB-2025-000037,JOB-2025-000038 | D111: /portal-busquedas/ | J111: https://lnkd.in/ | K111: Mozilla/5.0 (Windows NT 10.0; Win64; x64) AppleWebKit/537.36 (KHTML, like Gecko) Chrome/146.0.0.0 Safari/537.36 Edg/146.0.0.0 | L111: desktop | M111: 485f722a-d223-4ddc-8c2e-175de81fcec0 | N111: NO
A112: 46115.546 | B112: view_job | C112: JOB-2025-000037 | D112: /portal-busquedas/ | J112: https://lnkd.in/ | K112: Mozilla/5.0 (Windows NT 10.0; Win64; x64) AppleWebKit/537.36 (KHTML, like Gecko) Chrome/146.0.0.0 Safari/537.36 Edg/146.0.0.0 | L112: desktop | M112: 485f722a-d223-4ddc-8c2e-175de81fcec0 | N112: NO
A113: 46115.545 | B113: page_view | D113: /portal-busquedas/ | K113: Mozilla/5.0 (iPhone; CPU iPhone OS 18_7 like Mac OS X) AppleWebKit/605.1.15 (KHTML, like Gecko) Version/26.3 Mobile/15E148 Safari/604.1 | L113: mobile | M113: e80f9a53-0a87-4ca9-bf21-74f8f1bbc6e4 | N113: NO
A114: 46115.544 | B114: page_view | D114: /portal-busquedas/ | J114: https://lnkd.in/ | K114: Mozilla/5.0 (Windows NT 10.0; Win64; x64) AppleWebKit/537.36 (KHTML, like Gecko) Chrome/146.0.0.0 Safari/537.36 Edg/146.0.0.0 | L114: desktop | M114: 485f722a-d223-4ddc-8c2e-175de81fcec0 | N114: NO
...
